{
  "country": "turkey",
  "last_updated": "2026-07-14T23:48:27Z",
  "stories": [
    {
      "title": "Condemnation from the Ministry of Foreign Affairs of the attack in Saudi Arabia",
      "source": "Sabah",
      "url": "https://www.sabah.com.tr/gundem/2026/07/14/disislerinden-suudi-arabistandaki-saldiriya-kinama",
      "published_date": "2026-07-14T19:05:31Z",
      "category": "Diplomacy"
    },
    {
      "title": "When will the Fed interest rate decision be announced?",
      "source": "Haberturk",
      "url": "https://www.haberturk.com/fed-faiz-karari-ne-zaman-aciklanacak-altin-ve-doviz-yatirimcisinin-gozu-kararda-fed-faizleri-yukseltecek-mi-3898375-ekonomi",
      "published_date": "2026-07-14T16:59:14Z",
      "category": "Diplomacy"
    },
    {
      "title": "Ukrainian Parliament approved the free trade agreement with Türkiye",
      "source": "Sabah",
      "url": "https://www.sabah.com.tr/ekonomi/ukrayna-parlamentosu-turkiye-ile-serbest-ticaret-anlasmasini-onayladi-7622400",
      "published_date": "2026-07-14T14:58:57Z",
      "category": "Diplomacy"
    },
    {
      "title": "Minister Fidan and UN Secretary General Guterres talked on the phone",
      "source": "Sabah",
      "url": "https://www.sabah.com.tr/dunya/bakan-fidan-ile-bm-genel-sekreteri-guterres-telefonda-gorustu-7622374",
      "published_date": "2026-07-14T13:59:49Z",
      "category": "Diplomacy"
    },
    {
      "title": "DenizBank signed the UN Principles of Responsible Banking",
      "source": "Haberturk",
      "url": "https://www.haberturk.com/denizbank-birlesmis-milletler-sorumlu-bankacilik-prensiplerine-imza-atti-3898434-ekonomi",
      "published_date": "2026-07-14T11:51:49Z",
      "category": "Diplomacy"
    },
    {
      "title": "He defended Victoria's lack of reaction",
      "source": "Haberturk",
      "url": "https://www.haberturk.com/david-beckham-esi-victoria-beckham-in-ingiltere-nin-dunya-kupasi-zaferindeki-tepkisizligini-savundu-3898363-magazin",
      "published_date": "2026-07-14T09:39:21Z",
      "category": "Diplomacy"
    },
    {
      "title": "Completed Ironman in 13 hours 30 minutes",
      "source": "Haberturk",
      "url": "https://www.haberturk.com/orkun-isitmak-ironman-vitoria-gasteiz-i-13-saat-30-dakikada-tamamladi-3898362-magazin",
      "published_date": "2026-07-14T09:28:45Z",
      "category": "Diplomacy"
    },
    {
      "title": "Nwaiwu to Fulham step by step!",
      "source": "Haberturk",
      "url": "https://www.haberturk.com/chibuike-nwaiwu-adim-adim-fulham-a-3898372-spor",
      "published_date": "2026-07-14T09:25:12Z",
      "category": "Diplomacy"
    },
    {
      "title": "Bahçeli: NATO is at the dawn of a new era",
      "source": "Haberturk",
      "url": "https://www.haberturk.com/son-dakika-haberleri-mhp-lideri-bahceli-nato-yeni-devrin-safaginda-3898317",
      "published_date": "2026-07-14T09:02:45Z",
      "category": "Diplomacy"
    },
    {
      "title": "7-year-old Harun's joy with bionic ears",
      "source": "Haberturk",
      "url": "https://www.haberturk.com/7-yasindaki-harun-un-biyonik-kulak-sevinci-haberler-3898336",
      "published_date": "2026-07-14T08:00:02Z",
      "category": "Diplomacy"
    },
    {
      "title": "Last Minute | MHP leader Devlet Bahçeli: It is a mistake to think that the FETO threat has completely disappeared",
      "source": "Sabah",
      "url": "https://www.sabah.com.tr/gundem/2026/07/14/son-dakika-mhp-lideri-devlet-bahceliden-onemli-aciklamalar",
      "published_date": "2026-07-14T07:32:31Z",
      "category": "Diplomacy"
    },
    {
      "title": "Lindsey Graham's sister was appointed to the seat vacated",
      "source": "Haberturk",
      "url": "https://www.haberturk.com/yeni-senator-graham-in-kiz-kardesi-lindsey-graham-dan-bosalan-koltuga-darline-graham-atandi-3898312",
      "published_date": "2026-07-14T07:05:26Z",
      "category": "Diplomacy"
    },
    {
      "title": "'Reşo Ağa' and 15 people were detained",
      "source": "Haberturk",
      "url": "https://www.haberturk.com/son-dakika-reso-aga-ve-15-kisi-gozaltina-alindi-3898291",
      "published_date": "2026-07-14T06:34:51Z",
      "category": "Diplomacy"
    },
    {
      "title": "The new favorite of the coffee world: Turkish Latte!",
      "source": "Haberturk",
      "url": "https://www.haberturk.com/bir-fincanla-yetinemeyeceksiniz-sosyal-medyanin-yeni-gozdesi-turkish-latte-nin-tarifi-ve-puf-noktalari-3897317",
      "published_date": "2026-07-14T06:15:27Z",
      "category": "Diplomacy"
    },
    {
      "title": "It will lay off 100 thousand people",
      "source": "Haberturk",
      "url": "https://www.haberturk.com/volkswagen-100-bin-kisiyi-isten-cikaracak-3898281-ekonomi",
      "published_date": "2026-07-14T06:01:31Z",
      "category": "Diplomacy"
    },
    {
      "title": "'Elite' stars are in Türkiye",
      "source": "Haberturk",
      "url": "https://www.haberturk.com/elite-yildizlari-georgina-amors-ve-manu-rios-turkiye-de-tatil-yapiyor-3898256-magazin",
      "published_date": "2026-07-14T05:17:48Z",
      "category": "Diplomacy"
    },
    {
      "title": "Trump supports Saudi Crown Prince",
      "source": "Haberturk",
      "url": "https://www.haberturk.com/trump-suudi-veliaht-prensi-ne-destek-verdi-3898283",
      "published_date": "2026-07-14T05:17:43Z",
      "category": "Diplomacy"
    },
    {
      "title": "Trump: Attacks on Iran will continue, agreement is possible",
      "source": "Haberturk",
      "url": "https://www.haberturk.com/trump-iran-a-saldirilar-surecek-anlasma-mumkun-3898278",
      "published_date": "2026-07-14T04:34:36Z",
      "category": "Diplomacy"
    },
    {
      "title": "Why are leaders' toilet waste taken back to their countries?",
      "source": "Haberturk",
      "url": "https://www.haberturk.com/zirhli-araclar-ve-koruma-ordusu-yetmedi-tuvaletleri-bile-ozel-koruma-altinda-dunya-liderlerinin-biyolojik-atiklari-neden-ulkelerine-goturuluyor-3897813",
      "published_date": "2026-07-14T04:26:14Z",
      "category": "Diplomacy"
    },
    {
      "title": "The cost of Greenwood has been announced!",
      "source": "Haberturk",
      "url": "https://www.haberturk.com/mason-greenwood-adim-adim-fenerbahce-ye-maliyeti-belli-oldu-3898262-spor",
      "published_date": "2026-07-13T21:55:27Z",
      "category": "Diplomacy"
    },
    {
      "title": "Negotiations of the 12th Judicial Package started at the Turkish Grand National Assembly General Assembly",
      "source": "Haberturk",
      "url": "https://www.haberturk.com/tbmm-genel-kurulu-nda-12-yargi-paketi-nin-gorusmeleri-basladi-3898564",
      "published_date": "2026-07-14T22:56:33Z",
      "category": "Military"
    },
    {
      "title": "10 years have passed since FETO's coup attempt: July 15 messages from members of the Presidential Cabinet",
      "source": "Sabah",
      "url": "https://www.sabah.com.tr/gundem/2026/07/14/fetonun-darbe-girisiminin-uzerinden-10-yil-gecti-cumhurbaskanligi-kabinesi-uyelerinden-15-temmuz-mesajlari",
      "published_date": "2026-07-14T20:25:12Z",
      "category": "Military"
    },
    {
      "title": "Murat Kurum: \"A heroic epic was written under the leadership of our President\"",
      "source": "Sabah",
      "url": "https://www.sabah.com.tr/gundem/2026/07/14/murat-kurum-cumhurbaskanimizin-liderliginde-bir-kahramanlik-destani-yazildi",
      "published_date": "2026-07-14T20:00:40Z",
      "category": "Military"
    },
    {
      "title": "New order from Donald Trump to Netanyahu: \"Withdraw from Lebanon and Israel\"",
      "source": "Sabah",
      "url": "https://www.sabah.com.tr/dunya/donald-trumptan-netanyahuya-yeni-emir-lubnan-ve-israilden-cekil-7622535",
      "published_date": "2026-07-14T18:55:19Z",
      "category": "Military"
    },
    {
      "title": "Reactions to Netanyahu are growing: Protested in the Parliament!",
      "source": "Sabah",
      "url": "https://www.sabah.com.tr/dunya/netanyahuya-tepkiler-buyuyor-mecliste-protesto-edildi-7622415",
      "published_date": "2026-07-14T15:35:46Z",
      "category": "Military"
    },
    {
      "title": "Roaming cooperation from Trugo and Oncharge",
      "source": "Haberturk",
      "url": "https://www.haberturk.com/trugo-ve-onchargedan-roaming-is-birligi-3898491-ekonomi",
      "published_date": "2026-07-14T14:16:46Z",
      "category": "Military"
    },
    {
      "title": "Killer Israel hit a police post in Gaza: 6 Palestinians lost their lives",
      "source": "Sabah",
      "url": "https://www.sabah.com.tr/dunya/katil-israil-gazzede-polis-noktasini-vurdu-6-filistinli-yasamini-yitirdi-7622347",
      "published_date": "2026-07-14T13:05:24Z",
      "category": "Military"
    },
    {
      "title": "Warning from Australia to technology giants: You failed to protect children",
      "source": "Sabah",
      "url": "https://www.sabah.com.tr/dunya/avustralyadan-teknoloji-devlerine-uyari-cocuklari-korumakta-yetersiz-kaldiniz-7622322",
      "published_date": "2026-07-14T12:31:33Z",
      "category": "Military"
    },
    {
      "title": "Ministry of Internal Affairs announced! Heavy blow to immigrant smuggling in 26 provinces: 57 suspects caught!",
      "source": "Sabah",
      "url": "https://www.sabah.com.tr/gundem/2026/07/14/icisleri-bakanligi-duyurdu-26-ilde-gocmen-kacakciligina-agir-darbe-57-supheli-kiskivrak-yakalandi",
      "published_date": "2026-07-14T11:51:06Z",
      "category": "Military"
    },
    {
      "title": "Operation in 26 provinces: 43 arrests",
      "source": "Haberturk",
      "url": "https://www.haberturk.com/son-dakika-26-ilde-gocmen-kacakciligi-ile-mucadele-operasyonu-43-tutuklama-3898427",
      "published_date": "2026-07-14T11:39:27Z",
      "category": "Military"
    },
    {
      "title": "Emergency landing on a grassy area in Washington: Military helicopter alerted",
      "source": "Sabah",
      "url": "https://www.sabah.com.tr/dunya/washingtonda-cimlik-alana-acil-inis-askeri-helikopter-alarma-gecirdi-7622248",
      "published_date": "2026-07-14T10:03:02Z",
      "category": "Military"
    },
    {
      "title": "\"Additional treatment\" warning in in vitro fertilization!",
      "source": "Haberturk",
      "url": "https://www.haberturk.com/tup-bebekte-ek-tedavi-uyarisi-3898367",
      "published_date": "2026-07-14T09:25:55Z",
      "category": "Military"
    },
    {
      "title": "Tension rose on the US-Iran line",
      "source": "Haberturk",
      "url": "https://www.haberturk.com/abd-iran-hattinda-tansiyon-yukseldi-3898276",
      "published_date": "2026-07-14T09:21:42Z",
      "category": "Military"
    },
    {
      "title": "FETO operation: 704 detained",
      "source": "Haberturk",
      "url": "https://www.haberturk.com/son-dakika-81-ilde-feto-operasyonu-704-gozalti-3898347",
      "published_date": "2026-07-14T08:38:08Z",
      "category": "Military"
    },
    {
      "title": "Counterfeit liquor operation in Niğde: 6 detained",
      "source": "Haberturk",
      "url": "https://www.haberturk.com/nigde-de-sahte-icki-operasyonu-6-gozalti-3898354",
      "published_date": "2026-07-14T08:34:11Z",
      "category": "Military"
    },
    {
      "title": "President Erdoğan received Pakistan Defense Forces Commander Munir",
      "source": "Sabah",
      "url": "https://www.sabah.com.tr/gundem/2026/07/14/baskan-erdogan-pakistan-savunma-kuvvetleri-komutani-muniri-kabul-etti",
      "published_date": "2026-07-14T08:29:00Z",
      "category": "Military"
    },
    {
      "title": "Received the Commander of Pakistan Defense Forces",
      "source": "Haberturk",
      "url": "https://www.haberturk.com/cumhurbaskani-erdogan-pakistan-savunma-kuvvetleri-komutani-ve-kara-kuvvetleri-komutani-munir-i-kabul-3898340",
      "published_date": "2026-07-14T08:03:04Z",
      "category": "Military"
    },
    {
      "title": "Temperatures increased, Prof. Dr. Özzlü warned!",
      "source": "Haberturk",
      "url": "https://www.haberturk.com/prof-dr-ozlu-den-klima-uyarisi-haberler-3898330",
      "published_date": "2026-07-14T07:37:10Z",
      "category": "Military"
    },
    {
      "title": "Oil prices rose again",
      "source": "Haberturk",
      "url": "https://www.haberturk.com/gerilim-artti-petrol-fiyatlari-yeniden-yukseldi-3898285-ekonomi",
      "published_date": "2026-07-14T06:19:25Z",
      "category": "Military"
    },
    {
      "title": "States block the $108 billion giant merger",
      "source": "Haberturk",
      "url": "https://www.haberturk.com/hollywood-daki-108-milyar-dolarlik-dev-birlesmeye-eyaletlerden-engel-3898290-teknoloji",
      "published_date": "2026-07-14T06:10:39Z",
      "category": "Military"
    },
    {
      "title": "Blood-curdling child brutality in Kırıkkale: He killed his father and cut him into pieces!",
      "source": "Sabah",
      "url": "https://www.sabah.com.tr/yasam/kirikkalede-kan-donduran-evlat-vahseti-babasini-oldurup-parcalara-ayirdi-7622559",
      "published_date": "2026-07-14T19:29:23Z",
      "category": "Energy"
    },
    {
      "title": "xAI gas turbines emit pollution!",
      "source": "Haberturk",
      "url": "https://www.haberturk.com/muskin-xaisi-izinsiz-59-gaz-turbini-kurdu-3898443-teknoloji",
      "published_date": "2026-07-14T12:29:04Z",
      "category": "Energy"
    },
    {
      "title": "The new danger awaiting the world: Not oil, but diesel crisis is at the door",
      "source": "Haberturk",
      "url": "https://www.haberturk.com/dunyayi-bekleyen-yeni-tehlike-petrol-degil-motorin-krizi-kapida-3898369-ekonomi",
      "published_date": "2026-07-14T10:17:46Z",
      "category": "Energy"
    },
    {
      "title": "TMO purchased 5 million tons of grain",
      "source": "Sabah",
      "url": "https://www.sabah.com.tr/ekonomi/tmo-5-milyon-ton-hububat-aldi-7622231",
      "published_date": "2026-07-14T09:36:05Z",
      "category": "Energy"
    },
    {
      "title": "New energy formula from Turkey to Iraq! Old agreement ends, negotiation for new oil pipeline",
      "source": "Sabah",
      "url": "https://www.sabah.com.tr/ekonomi/turkiyeden-iraka-yeni-enerji-formulu-eski-anlasma-bitiyor-yeni-petrol-hatti-icin-muzakere-7622213",
      "published_date": "2026-07-14T09:06:03Z",
      "category": "Energy"
    },
    {
      "title": "Statement from Minister Bayraktar on Türkiye-Iraq Pipeline",
      "source": "Haberturk",
      "url": "https://www.haberturk.com/bakan-bayraktardan-turkiye-irak-boru-hatti-aciklamasi-yeni-bir-anlasma-olmasi-lazim-3898346-ekonomi",
      "published_date": "2026-07-14T09:02:19Z",
      "category": "Energy"
    },
    {
      "title": "Combined cycle of the first phase of Kumasi Power Plant has been completed",
      "source": "Haberturk",
      "url": "https://www.haberturk.com/kumasi-santralinin-ilk-fazinin-kombine-cevrimi-tamamlandi-3898355-ekonomi",
      "published_date": "2026-07-14T08:36:54Z",
      "category": "Energy"
    },
    {
      "title": "\"Adaptation and Resilience\" themed bond issuance from Garanti BBVA",
      "source": "Haberturk",
      "url": "https://www.haberturk.com/garanti-bbvadan-adaptasyon-ve-dayaniklilik-temali-30-milyon-dolarlik-surdurulebilir-tahvil-ihraci-3898172-ekonomi",
      "published_date": "2026-07-13T12:52:40Z",
      "category": "Energy"
    },
    {
      "title": "Big increase from OPEC: Production increased by 3.05 million barrels",
      "source": "Sabah",
      "url": "https://www.sabah.com.tr/ekonomi/opecten-buyuk-artis-uretim-305-milyon-varil-yukseldi-7621636",
      "published_date": "2026-07-13T12:49:38Z",
      "category": "Energy"
    },
    {
      "title": "World Bank message from Minister Bayraktar: We are developing concrete projects that will accelerate the energy transition",
      "source": "Sabah",
      "url": "https://www.sabah.com.tr/ekonomi/bakan-bayraktardan-dunya-bankasi-mesaji-enerji-donusumunu-hizlandiracak-somut-projeler-gelistiriyoruz-7621595",
      "published_date": "2026-07-13T11:47:25Z",
      "category": "Energy"
    },
    {
      "title": "Lentils without tillage were harvested",
      "source": "Haberturk",
      "url": "https://www.haberturk.com/toprak-islemesiz-mercimegin-hasadi-yapildi-3898130",
      "published_date": "2026-07-13T10:39:52Z",
      "category": "Energy"
    },
    {
      "title": "Minister Bayraktar announced: New investment in Turkey's LNG power: Storage capacity at Marmaraereğlisi Terminal will increase to 415 thousand cubic meters",
      "source": "Sabah",
      "url": "https://www.sabah.com.tr/ekonomi/bakan-bayraktar-acikladi-turkiyenin-lng-gucune-yeni-yatirim-marmaraereglisi-terminalinde-depolama-kapasitesi-415-bin-metrekupe-cikacak-7621545",
      "published_date": "2026-07-13T09:18:44Z",
      "category": "Energy"
    },
    {
      "title": "USA launches new attack on Iran",
      "source": "Haberturk",
      "url": "https://www.haberturk.com/abd-iran-a-yeni-saldiri-baslatti-3898008",
      "published_date": "2026-07-13T03:23:34Z",
      "category": "Energy"
    },
    {
      "title": "PTT's electric scooters delivered 89.6 million shipments to their owners",
      "source": "Sabah",
      "url": "https://www.sabah.com.tr/ekonomi/pttnin-elektrikli-skuterleri-896-milyon-gonderiyi-sahiplerine-ulastirdi-7621021",
      "published_date": "2026-07-12T09:28:57Z",
      "category": "Energy"
    },
    {
      "title": "This flavor shakes Matcha's throne!",
      "source": "Haberturk",
      "url": "https://www.haberturk.com/matcha-nin-tahti-sallantida-kafelerin-yeni-gozdesi-pastel-mor-lezzet-ube-ile-tanisin-iste-faydalari-ve-ube-latte-tarifi-3896548",
      "published_date": "2026-07-11T09:50:32Z",
      "category": "Energy"
    },
    {
      "title": "400 kg of plain oil was confiscated in Şanlıurfa",
      "source": "Haberturk",
      "url": "https://www.haberturk.com/sanliurfa-da-400-kg-sade-yaga-el-konuldu-3897772",
      "published_date": "2026-07-11T09:30:15Z",
      "category": "Energy"
    },
    {
      "title": "\"Memorandum of Understanding on Natural Gas Supply to TRNC\" was signed between Türkiye and TRNC",
      "source": "Haberturk",
      "url": "https://www.haberturk.com/turkiye-ile-kktc-arasinda-kktc-ye-dogalgaz-tedarikine-dair-mutabakat-zapti-imzalandi-3897768-ekonomi",
      "published_date": "2026-07-11T09:22:08Z",
      "category": "Energy"
    },
    {
      "title": "Electric grid collapsed for the second time in Cuba",
      "source": "Sabah",
      "url": "https://www.sabah.com.tr/dunya/kubada-elektrik-sebekesi-ikinci-kez-coktu-7620431",
      "published_date": "2026-07-11T09:10:36Z",
      "category": "Energy"
    },
    {
      "title": "Don't make these 9 mistakes in the refrigerator!",
      "source": "Haberturk",
      "url": "https://www.haberturk.com/sutu-yumurtayi-ve-cig-eti-yanlis-rafa-koyuyor-olabilirsiniz-iste-buzdolabinda-en-sik-yapilan-9-yerlestirme-hatasi-3895115",
      "published_date": "2026-07-11T08:17:20Z",
      "category": "Energy"
    },
    {
      "title": "New investment move of 2,400 megawatts in renewable energy! The button was pressed for the 21 YEKA competition",
      "source": "Sabah",
      "url": "https://www.sabah.com.tr/ekonomi/yenilenebilir-enerjide-2400-megavatlik-yeni-yatirim-hamlesi-21-yeka-yarismasi-icin-dugmeye-basildi-7620398",
      "published_date": "2026-07-11T08:08:51Z",
      "category": "Energy"
    },
    {
      "title": "Sharp rise in gold",
      "source": "Haberturk",
      "url": "https://www.haberturk.com/altin-fiyatlari-son-durum-14-temmuz-gram-altin-6-bin-100-liranin-altini-gordu-ceyrek-ve-gram-altin-fiyatlari-ne-kadar-kac-tl-3898288-ekonomi",
      "published_date": "2026-07-14T21:35:07Z",
      "category": "Economy"
    },
    {
      "title": "The lowest pension article was passed by the commission",
      "source": "Haberturk",
      "url": "https://www.haberturk.com/son-dakika-en-dusuk-emekli-ayligi-maddesi-komisyondan-gecti-3898517-ekonomi",
      "published_date": "2026-07-14T20:29:52Z",
      "category": "Economy"
    },
    {
      "title": "Striking statement from Fed President Warsh: \"We need regime change\"",
      "source": "Sabah",
      "url": "https://www.sabah.com.tr/dunya/fed-baskani-warshtan-carpici-aciklama-rejim-degisikligine-ihtiyacimiz-var-7622508",
      "published_date": "2026-07-14T18:21:47Z",
      "category": "Economy"
    },
    {
      "title": "All eyes on US inflation data",
      "source": "Haberturk",
      "url": "https://www.haberturk.com/abd-enflasyon-verileri-ne-zaman-aciklanacak-beklentiler-yukari-yonde-abd-enflasyon-orani-yuzde-kac-olacak-3898400-ekonomi",
      "published_date": "2026-07-14T17:00:24Z",
      "category": "Economy"
    },
    {
      "title": "Artaş İnşaat was among the top 100 companies paying the highest corporate taxes in Istanbul.",
      "source": "Sabah",
      "url": "https://www.sabah.com.tr/ekonomi/artas-insaat-istanbulda-en-yuksek-kurumlar-vergisi-odeyen-sirketler-arasinda-ilk-100de-yer-aldi-7622456",
      "published_date": "2026-07-14T16:43:03Z",
      "category": "Economy"
    },
    {
      "title": "OECD report: Türkiye ranks first in real wage increase in the last 5 years",
      "source": "Haberturk",
      "url": "https://www.haberturk.com/oecd-raporu-turkiye-son-5-yilda-reel-ucret-artisinda-ilk-sirada-3898519-ekonomi",
      "published_date": "2026-07-14T16:19:05Z",
      "category": "Economy"
    },
    {
      "title": "The stock market ended the day with a decline",
      "source": "Haberturk",
      "url": "https://www.haberturk.com/borsa-gunu-dususle-tamamladi-3898512-ekonomi",
      "published_date": "2026-07-14T15:47:07Z",
      "category": "Economy"
    },
    {
      "title": "New loan package of 250 billion lira for industrialists",
      "source": "Haberturk",
      "url": "https://www.haberturk.com/sanayiciye-250-milyar-liralik-yeni-kredi-paketi-3898490-ekonomi",
      "published_date": "2026-07-14T14:20:43Z",
      "category": "Economy"
    },
    {
      "title": "Historical decline in IBM",
      "source": "Haberturk",
      "url": "https://www.haberturk.com/ibm-de-tarihi-dusus-40-yilin-en-kotu-gunu-3898483-teknoloji",
      "published_date": "2026-07-14T14:00:52Z",
      "category": "Economy"
    },
    {
      "title": "Negative inflation in the USA",
      "source": "Haberturk",
      "url": "https://www.haberturk.com/abd-de-enflasyon-beklentinin-altinda-3898463-ekonomi",
      "published_date": "2026-07-14T13:24:54Z",
      "category": "Economy"
    },
    {
      "title": "Sharp rise in gold",
      "source": "Haberturk",
      "url": "https://www.haberturk.com/altinda-sert-yukselis-3898462-ekonomi",
      "published_date": "2026-07-14T13:22:00Z",
      "category": "Economy"
    },
    {
      "title": "Ambitious inflation statement from the Fed",
      "source": "Haberturk",
      "url": "https://www.haberturk.com/fed-baskani-warsh-enflasyon-gecmiste-kalacak-3898471-ekonomi",
      "published_date": "2026-07-14T13:11:27Z",
      "category": "Economy"
    },
    {
      "title": "Critical data for gold and silver has been announced! Inflation did not meet expectations in the USA",
      "source": "Sabah",
      "url": "https://www.sabah.com.tr/finans/ekonomi/altin-ve-gumus-icin-kritik-veri-aciklandi-abdde-enflasyon-beklentileri-karsilamadi-7622341",
      "published_date": "2026-07-14T12:58:10Z",
      "category": "Economy"
    },
    {
      "title": "BREAKING NEWS: New production and investment move from the economic management: 250 billion lira loan package is coming",
      "source": "Sabah",
      "url": "https://www.sabah.com.tr/ekonomi/son-dakika-ekonmomi-yonetiminden-is-gucu-ve-yatirim-mesaji-7622292",
      "published_date": "2026-07-14T11:34:46Z",
      "category": "Economy"
    },
    {
      "title": "\"Türkiye is a strategic country for Mango\"",
      "source": "Haberturk",
      "url": "https://www.haberturk.com/turkiye-mango-icin-stratejik-bir-ulke-3898424-ekonomi",
      "published_date": "2026-07-14T11:30:11Z",
      "category": "Economy"
    },
    {
      "title": "The analysis was published in Forbes",
      "source": "Haberturk",
      "url": "https://www.haberturk.com/turkiyenin-doa-sistemi-abd-ve-batili-ulkelere-ornek-gosterildi-3898395-ekonomi",
      "published_date": "2026-07-14T10:35:37Z",
      "category": "Economy"
    },
    {
      "title": "Russia is looking for an alternative to the Sea of ​​Azov for grain exports",
      "source": "Sabah",
      "url": "https://www.sabah.com.tr/ekonomi/rusya-tahil-ihracatinda-azak-denizine-alternatif-ariyor-7622252",
      "published_date": "2026-07-14T10:15:48Z",
      "category": "Economy"
    },
    {
      "title": "What is the minimum pension?",
      "source": "Haberturk",
      "url": "https://www.haberturk.com/emekli-maasi-hesaplama-2026-temmuz-zammi-en-dusuk-emekli-maasi-ne-kadar-olacak-emekli-maasi-resmi-gazete-de-ne-zaman-yayimlanacak-3897974",
      "published_date": "2026-07-14T09:53:30Z",
      "category": "Economy"
    },
    {
      "title": "Guard recruitment application dates",
      "source": "Haberturk",
      "url": "https://www.haberturk.com/bekci-alimi-2026-ne-zaman-basvuru-tarihleri-belli-oldu-mu-egm-ile-carsi-ve-mahalle-bekciligi-sartlari-ne-zamli-bekci-maasi-ne-kadar-3897589",
      "published_date": "2026-07-14T09:53:09Z",
      "category": "Economy"
    },
    {
      "title": "\"We will continue to support production\"",
      "source": "Haberturk",
      "url": "https://www.haberturk.com/bakan-simsek-uretimi-desteklemeye-devam-edecegiz-3898385-ekonomi",
      "published_date": "2026-07-14T09:52:36Z",
      "category": "Economy"
    },
    {
      "title": "Special: The nation is looking for hope in the new party",
      "source": "Haberturk",
      "url": "https://www.haberturk.com/ozel-millet-umudunu-yeni-partide-ariyor-3898562",
      "published_date": "2026-07-14T22:21:34Z",
      "category": "Local Events"
    },
    {
      "title": "Devlet Bahçeli: \"July 15 is a multi-layered invasion attempt\"",
      "source": "Sabah",
      "url": "https://www.sabah.com.tr/gundem/2026/07/14/devlet-bahceli-15-temmuz-cok-katmanli-bir-isgal-tesebbusudur",
      "published_date": "2026-07-14T22:03:59Z",
      "category": "Local Events"
    },
    {
      "title": "July 15 messages from the cabinet",
      "source": "Haberturk",
      "url": "https://www.haberturk.com/kabineden-15-temmuz-mesajlari-3898560",
      "published_date": "2026-07-14T22:00:09Z",
      "category": "Local Events"
    },
    {
      "title": "July 15 message from MHP leader Bahçeli",
      "source": "Haberturk",
      "url": "https://www.haberturk.com/mhp-lideri-bahceli-den-15-temmuz-mesaji-3898558",
      "published_date": "2026-07-14T21:46:07Z",
      "category": "Local Events"
    },
    {
      "title": "15 July Democracy and National Unity Day messages from the sports community!",
      "source": "Sabah",
      "url": "https://www.sabah.com.tr/spor/futbol/2026/07/14/spor-camiasindan-15-temmuz-demokrasi-ve-milli-birlik-gunu-mesajlari",
      "published_date": "2026-07-14T21:10:17Z",
      "category": "Local Events"
    },
    {
      "title": "Cevdet Yılmaz: \"Our nation has demonstrated one of the most glorious resistances in our history\"",
      "source": "Sabah",
      "url": "https://www.sabah.com.tr/gundem/2026/07/14/cevdet-yilmaz-milletimiz-tarihimizin-en-sanli-direnislerinden-birini-ortaya-koymustur",
      "published_date": "2026-07-14T19:54:42Z",
      "category": "Local Events"
    },
    {
      "title": "15 July Democracy and National Unity Day message from Efkan Ala",
      "source": "Sabah",
      "url": "https://www.sabah.com.tr/gundem/2026/07/14/efkan-aladan-15-temmuz-demokrasi-ve-milli-birlik-gunu-mesaji",
      "published_date": "2026-07-14T19:50:55Z",
      "category": "Local Events"
    },
    {
      "title": "The nation cannot bend, Türkiye cannot be surpassed! Epic victory is 10 years old",
      "source": "Sabah",
      "url": "https://www.sabah.com.tr/gundem/2026/07/14/millet-egilmez-turkiye-gecilmez-destansi-zafer-10-yasinda",
      "published_date": "2026-07-14T19:48:30Z",
      "category": "Local Events"
    },
    {
      "title": "President Erdoğan returned home!",
      "source": "Sabah",
      "url": "https://www.sabah.com.tr/gundem/2026/07/14/baskan-erdogan-yurda-dondu",
      "published_date": "2026-07-14T18:44:04Z",
      "category": "Local Events"
    },
    {
      "title": "July 15 post from AK Party: \"This homeland belongs to those who are conscious of the truth\"",
      "source": "Sabah",
      "url": "https://www.sabah.com.tr/gundem/2026/07/14/ak-partiden-15-temmuz-paylasimi-bu-vatan-asim-suuruna-erenlerindir",
      "published_date": "2026-07-14T18:36:49Z",
      "category": "Local Events"
    },
    {
      "title": "Remarkable statement from Trump on Iraq: \"USA attacked the wrong country\"",
      "source": "Sabah",
      "url": "https://www.sabah.com.tr/dunya/trumptan-dikkat-ceken-irak-aciklamasi-abd-yanlis-ulkeye-saldirdi-7622509",
      "published_date": "2026-07-14T18:23:19Z",
      "category": "Local Events"
    },
    {
      "title": "6.2 magnitude earthquake in the Philippines",
      "source": "Sabah",
      "url": "https://www.sabah.com.tr/dunya/filipinlerde-62-buyuklugunde-deprem-7622502",
      "published_date": "2026-07-14T18:12:26Z",
      "category": "Local Events"
    },
    {
      "title": "BREAKING NEWS I Corruption investigation against CHP's Çankaya Municipality: Arrest request for 31 people, including Mayor Güner!",
      "source": "Sabah",
      "url": "https://www.sabah.com.tr/gundem/2026/07/14/son-dakika-i-chpli-cankaya-belediyesine-yolsuzluk-sorusturmasi-baskan-guner-dahil-31-kisiye-tutuklama-talebi",
      "published_date": "2026-07-14T17:28:32Z",
      "category": "Local Events"
    },
    {
      "title": "Spain reached the final of the World Cup! France was destroyed",
      "source": "Sabah",
      "url": "https://www.sabah.com.tr/spor/futbol/2026/07/14/ispanya-dunya-kupasinda-finale-cikti-fransa-yikildi",
      "published_date": "2026-07-14T17:13:01Z",
      "category": "Local Events"
    },
    {
      "title": "Ukrainian Parliament approved Prime Minister Sviridenko's resignation petition",
      "source": "Sabah",
      "url": "https://www.sabah.com.tr/dunya/ukrayna-parlamentosu-basbakan-sviridenkonun-istifa-dilekcesini-onayladi-7622413",
      "published_date": "2026-07-14T15:30:47Z",
      "category": "Local Events"
    },
    {
      "title": "We have not forgotten, we will not let you forget: 100 events on the 10th anniversary of July 15",
      "source": "Sabah",
      "url": "https://www.sabah.com.tr/gundem/2026/07/14/15-temmuzun-10-yilinda-100-etkinlik-1784048750",
      "published_date": "2026-07-14T15:10:40Z",
      "category": "Local Events"
    },
    {
      "title": "Recitation and meaning of Surah Amenerrasulu",
      "source": "Haberturk",
      "url": "https://www.haberturk.com/amenerresulu-suresi-okunusu-ve-turkce-anlami-amenerresulu-duasi-tefsiri-arapca-yazilisi-ve-fazileti-3665449",
      "published_date": "2026-07-14T14:49:19Z",
      "category": "Local Events"
    },
    {
      "title": "How to perform the night prayer?",
      "source": "Haberturk",
      "url": "https://www.haberturk.com/yatsi-namazi-kilinisi-erkek-ve-kadin-yatsi-namazi-nasil-kilinir-kac-rekat-hangi-dualar-ve-sureler-okunur-saat-kacta-kilinmali-3626840",
      "published_date": "2026-07-14T14:46:25Z",
      "category": "Local Events"
    },
    {
      "title": "How to perform ablution?",
      "source": "Haberturk",
      "url": "https://www.haberturk.com/abdest-nasil-alinir-namaz-abdesti-nasil-alinir-sirasi-ve-farzlari-neler-kadin-ve-erkek-htka-3634003",
      "published_date": "2026-07-14T14:44:30Z",
      "category": "Local Events"
    },
    {
      "title": "2nd wave in the AHBAP investigation",
      "source": "Haberturk",
      "url": "https://www.haberturk.com/son-dakika-ahbap-sorusturmasinda-17-yeni-gozalti-karari-3898294",
      "published_date": "2026-07-14T14:12:22Z",
      "category": "Local Events"
    }
  ]
}