{
  "country": "turkey",
  "last_updated": "2026-03-30T15:00:08Z",
  "stories": [
    {
      "title": "Compensation lawsuit from President Erdoğan to Özgür Özel",
      "source": "Sabah",
      "url": "https://www.sabah.com.tr/gundem/2026/03/30/baskan-erdogandan-ozgur-ozele-tazminat-davasi",
      "published_date": "2026-03-30T14:00:56Z",
      "category": "Diplomacy"
    },
    {
      "title": "EU approves Italy's 6 billion Euro hydrogen support plan",
      "source": "Haberturk",
      "url": "https://www.haberturk.com/ab-italyanin-6-milyar-euro-luk-hidrojen-destek-planina-onay-verdi-3873472-ekonomi",
      "published_date": "2026-03-30T13:35:54Z",
      "category": "Diplomacy"
    },
    {
      "title": "Breaking news! New threat from Trump to Tehran administration: If there is no agreement, we will destroy Iran",
      "source": "Sabah",
      "url": "https://www.sabah.com.tr/yasam/canli-son-dakika-donald-trumptan-yeni-mesaj-iranda-bircok-hedef-imha-edildi-tahrandan-israile-sok-misilleme-7553279",
      "published_date": "2026-03-30T11:47:00Z",
      "category": "Diplomacy"
    },
    {
      "title": "\"International Zero Waste Day\" message from First Lady Erdoğan: We can also end world hunger!",
      "source": "Sabah",
      "url": "https://www.sabah.com.tr/gundem/2026/03/30/emine-erdogandan-uluslararasi-sifir-atik-gunu-mesaji",
      "published_date": "2026-03-30T09:38:23Z",
      "category": "Diplomacy"
    },
    {
      "title": "Day 12 in the corruption case of the century: Ceyhun Avşar is being cross-examined",
      "source": "Sabah",
      "url": "https://www.sabah.com.tr/yasam/asrin-yolsuzluk-davasinda-12-gun-7553340",
      "published_date": "2026-03-30T08:02:25Z",
      "category": "Diplomacy"
    },
    {
      "title": "International Zero Waste Day message from the Ministry of Foreign Affairs",
      "source": "Sabah",
      "url": "https://www.sabah.com.tr/gundem/2026/03/30/disisleri-bakanligindan-uluslararasi-sifir-atik-gunu-mesaji",
      "published_date": "2026-03-30T07:45:22Z",
      "category": "Diplomacy"
    },
    {
      "title": "Zero waste emphasis from Uraloğlu",
      "source": "Haberturk",
      "url": "https://www.haberturk.com/ulastirma-ve-altyapi-bakani-abdulkadir-uraloglu-daha-temiz-bir-gelecek-icin-calisiyoruz-3873352-ekonomi",
      "published_date": "2026-03-30T07:26:44Z",
      "category": "Diplomacy"
    },
    {
      "title": "A new era begins in communication",
      "source": "Haberturk",
      "url": "https://www.haberturk.com/iletisimde-yeni-donem-basliyor-3873365-teknoloji",
      "published_date": "2026-03-30T07:24:31Z",
      "category": "Diplomacy"
    },
    {
      "title": "Historical rally in oil",
      "source": "Haberturk",
      "url": "https://www.haberturk.com/petrolde-tarihi-ralli-3873317-ekonomi",
      "published_date": "2026-03-30T06:59:55Z",
      "category": "Diplomacy"
    },
    {
      "title": "Statement from OSD on integration with the EU",
      "source": "Haberturk",
      "url": "https://www.haberturk.com/osd-ab-ile-entegrasyonu-daha-ileriye-tasiyacagiz-3873096-ekonomi",
      "published_date": "2026-03-30T04:34:09Z",
      "category": "Diplomacy"
    },
    {
      "title": "Iran summit in Islamabad",
      "source": "Sabah",
      "url": "https://www.sabah.com.tr/dunya/islamabadda-iran-zirvesi-7553227",
      "published_date": "2026-03-30T04:01:30Z",
      "category": "Diplomacy"
    },
    {
      "title": "Latest situation in the US-Israel Iran War!",
      "source": "Haberturk",
      "url": "https://www.haberturk.com/abd-israil-iran-savasi-nda-son-durum-3873144",
      "published_date": "2026-03-30T01:53:34Z",
      "category": "Diplomacy"
    },
    {
      "title": "A UN Peacekeeper died in Lebanon",
      "source": "Haberturk",
      "url": "https://www.haberturk.com/lubnan-da-bir-bm-baris-gucu-askeri-oldu-3873299",
      "published_date": "2026-03-29T23:18:45Z",
      "category": "Diplomacy"
    },
    {
      "title": "'International Zero Waste Day' post from Minister Kurum",
      "source": "Sabah",
      "url": "https://www.sabah.com.tr/gundem/2026/03/29/bakan-kurumdan-uluslararasi-sifir-atik-gunu-paylasimi",
      "published_date": "2026-03-29T21:07:56Z",
      "category": "Diplomacy"
    },
    {
      "title": "International Zero Waste Day sharing from Emine Erdoğan",
      "source": "Sabah",
      "url": "https://www.sabah.com.tr/gundem/2026/03/29/emine-erdogandan-uluslararasi-sifir-atik-gunu-paylasimi",
      "published_date": "2026-03-29T20:03:16Z",
      "category": "Diplomacy"
    },
    {
      "title": "Have TOKİ Çorum draw results been announced?",
      "source": "Haberturk",
      "url": "https://www.haberturk.com/toki-corum-kura-tarihleri-ile-toki-corum-sonuclari-ne-zaman-aciklanacak-toki-corum-kura-cekilis-tarihi-ne-zaman-3873278",
      "published_date": "2026-03-29T19:04:59Z",
      "category": "Diplomacy"
    },
    {
      "title": "Minister Fidan was received by Pakistan Prime Minister Sharif",
      "source": "Sabah",
      "url": "https://www.sabah.com.tr/gundem/2026/03/29/bakan-fidan-pakistan-basbakani-serif-tarafindan-kabul-edildi",
      "published_date": "2026-03-29T18:21:11Z",
      "category": "Diplomacy"
    },
    {
      "title": "An investigation has been launched against CHP Chairman Özgür Özel",
      "source": "Sabah",
      "url": "https://www.sabah.com.tr/gundem/2026/03/29/chp-genel-baskani-ozgur-ozel-hakkinda-sorusturma-baslatildi",
      "published_date": "2026-03-29T18:07:25Z",
      "category": "Diplomacy"
    },
    {
      "title": "Will there be a general amnesty with the 12th Judicial Package?",
      "source": "Haberturk",
      "url": "https://www.haberturk.com/12-yargi-paketi-son-gelismeler-2026-12-yargi-paketi-meclis-e-geldi-mi-ne-zaman-cikacak-12-yargi-paketi-maddeleri-ile-genel-af-cikacak-mi-3873270",
      "published_date": "2026-03-29T17:10:09Z",
      "category": "Diplomacy"
    },
    {
      "title": "He said, \"I don't want a widow in my house,\" and threw away the belongings!",
      "source": "Haberturk",
      "url": "https://www.haberturk.com/evimde-dul-kadin-istemiyorum-dedi-esyalari-atti-3873255",
      "published_date": "2026-03-29T14:58:18Z",
      "category": "Diplomacy"
    },
    {
      "title": "Ministry of National Defense: Missile fired from Iran was destroyed",
      "source": "Sabah",
      "url": "https://www.sabah.com.tr/yasam/msb-irandan-ateslenen-fuze-imha-edildi-7553528",
      "published_date": "2026-03-30T14:24:06Z",
      "category": "Military"
    },
    {
      "title": "Cross-border operation from MIT! Önder Sığırcıkoğlu, who carried out espionage activities against Türkiye, was caught",
      "source": "Sabah",
      "url": "https://www.sabah.com.tr/gundem/2026/03/30/mitten-sinir-otesinde-operasyon-turkiyeye-karsi-casusluk-faaliyetleri-yuruten-onder-sigircikoglu-yakalandi",
      "published_date": "2026-03-30T13:26:04Z",
      "category": "Military"
    },
    {
      "title": "Bloody ambush in the cemetery in Sarıyer: 1 dead, 1 injured in an armed conflict!",
      "source": "Sabah",
      "url": "https://www.sabah.com.tr/yasam/sariyerde-mezarlikta-kanli-pusu-silahli-catismada-1-olu-1-yarali-7553497",
      "published_date": "2026-03-30T12:50:18Z",
      "category": "Military"
    },
    {
      "title": "New cooperation step from Turkey with Canada in nuclear energy: CANDU technology is on the table",
      "source": "Sabah",
      "url": "https://www.sabah.com.tr/ekonomi/turkiyeden-kanada-ile-nukleer-enerjide-yeni-isbirligi-adimi-candu-teknolojisi-masada-7553481",
      "published_date": "2026-03-30T11:57:11Z",
      "category": "Military"
    },
    {
      "title": "Sustainability and zero waste studies from ASELSAN",
      "source": "Haberturk",
      "url": "https://www.haberturk.com/aselsan-dan-surdurulebilirlik-ve-sifir-atik-calismalari-3873434-teknoloji",
      "published_date": "2026-03-30T11:10:52Z",
      "category": "Military"
    },
    {
      "title": "'Zero Waste' message from Director of Communications Burhanettin Duran: Our common responsibility towards future generations",
      "source": "Sabah",
      "url": "https://www.sabah.com.tr/gundem/2026/03/30/iletisim-baskani-burhanettin-durandan-sifir-atik-mesaji-gelecek-nesillere-karsi-ortak-sorumlulugumuz",
      "published_date": "2026-03-30T11:00:09Z",
      "category": "Military"
    },
    {
      "title": "Applications for the 3rd term of the HUBrica Acceleration Program have started",
      "source": "Sabah",
      "url": "https://www.sabah.com.tr/ekonomi/hubrica-hizlandirma-programinin-3-donem-basvurulari-basladi-7553454",
      "published_date": "2026-03-30T10:35:35Z",
      "category": "Military"
    },
    {
      "title": "The child from Gaza who is not talked about as much as the \"monkey\": He struggled to carry loads heavier than himself",
      "source": "Sabah",
      "url": "https://www.sabah.com.tr/gundem/2026/03/30/maymun-kadar-konusulmayan-gazzeli-cocuk-kendinden-agir-yukleri-tasimak-icin-mucadele-etti",
      "published_date": "2026-03-30T08:55:28Z",
      "category": "Military"
    },
    {
      "title": "Iran announced: Revolutionary Guards Navy Commander Tengsiri lost his life",
      "source": "Sabah",
      "url": "https://www.sabah.com.tr/dunya/iran-acikladi-devrim-muhafizlari-donanma-komutani-tengsiri-yasamini-yitirdi-7553393",
      "published_date": "2026-03-30T08:44:49Z",
      "category": "Military"
    },
    {
      "title": "Call from Australia to the USA: Clarify your goals",
      "source": "Sabah",
      "url": "https://www.sabah.com.tr/dunya/avustralyadan-abdye-cagri-hedeflerinizi-netlestirin-7553377",
      "published_date": "2026-03-30T08:26:43Z",
      "category": "Military"
    },
    {
      "title": "Suspects of the 'bribery' operation in Marmaris were referred to the courthouse",
      "source": "Sabah",
      "url": "https://www.sabah.com.tr/gundem/2026/03/30/marmaristeki-rusvet-operasyonunun-suphelileri-adliyeye-sevk-edildi",
      "published_date": "2026-03-30T07:39:16Z",
      "category": "Military"
    },
    {
      "title": "Turkish Cargo will carry vivo products",
      "source": "Haberturk",
      "url": "https://www.haberturk.com/turkish-cargo-vivo-urunlerini-tasiyacak-3873353-teknoloji",
      "published_date": "2026-03-30T07:09:59Z",
      "category": "Military"
    },
    {
      "title": "They made public transportation free",
      "source": "Haberturk",
      "url": "https://www.haberturk.com/toplu-tasimayi-bedava-yaptilar-3873321-ekonomi",
      "published_date": "2026-03-30T05:34:44Z",
      "category": "Military"
    },
    {
      "title": "Pope's call for \"peace and disarmament\"",
      "source": "Sabah",
      "url": "https://www.sabah.com.tr/dunya/papadan-baris-ve-silahlarin-birakilmasi-cagrisi-7553225",
      "published_date": "2026-03-30T04:01:30Z",
      "category": "Military"
    },
    {
      "title": "Iran carried out more than 5 thousand attacks in a month",
      "source": "Haberturk",
      "url": "https://www.haberturk.com/iran-bir-ayda-5-binden-fazla-saldiri-duzenledi-3873301",
      "published_date": "2026-03-30T01:36:01Z",
      "category": "Military"
    },
    {
      "title": "45 billion dollars budget for the Ministry of Defense in Israel",
      "source": "Haberturk",
      "url": "https://www.haberturk.com/israil-de-savunma-bakanligi-na-45-milyar-dolar-butce-3873300",
      "published_date": "2026-03-30T00:00:09Z",
      "category": "Military"
    },
    {
      "title": "The brutality victim Kubilay Kaan Kundakçı was commemorated on the green field!",
      "source": "Haberturk",
      "url": "https://www.haberturk.com/vahset-kurbani-kubilay-kaan-kundakci-yesil-sahada-anildi-3873246",
      "published_date": "2026-03-29T14:16:38Z",
      "category": "Military"
    },
    {
      "title": "BİM 31 March-3 April current catalog",
      "source": "Haberturk",
      "url": "https://www.haberturk.com/bim-31-mart-3-nisan-aktuel-katalogu-bu-sali-ve-cuma-gunu-bim-marketlerde-hangi-urunler-satisa-cikiyor-indirimli-urunler-neler-3873233",
      "published_date": "2026-03-29T13:06:47Z",
      "category": "Military"
    },
    {
      "title": "Icardi returns to the starting 11 in Galatasaray!",
      "source": "Haberturk",
      "url": "https://www.haberturk.com/galatasaray-da-icardi-trabzonspor-maciyla-11-e-donuyor-3873218-spor",
      "published_date": "2026-03-29T11:40:56Z",
      "category": "Military"
    },
    {
      "title": "Intelligence wars and the information age! \"By achieving this, Türkiye rewrites the rules of war.\"",
      "source": "Sabah",
      "url": "https://www.sabah.com.tr/yasam/istihbarat-savaslari-ve-bilgi-cagi-bunu-basaran-turkiye-savasin-kurallarini-yeniden-yazar-7552833",
      "published_date": "2026-03-29T09:37:52Z",
      "category": "Military"
    },
    {
      "title": "Türkiye accelerates drilling activities",
      "source": "Haberturk",
      "url": "https://www.haberturk.com/turkiye-sondaj-calismalarini-hizlandiriyor-abdulhamid-han-fatih-ve-cagri-bey-gemileri-sahada-gorev-alacak-3873438-ekonomi",
      "published_date": "2026-03-30T12:03:38Z",
      "category": "Energy"
    },
    {
      "title": "Fuel demand peaked during the holiday! 34.7 billion TL was spent on diesel and 12.9 billion TL on gasoline.",
      "source": "Sabah",
      "url": "https://www.sabah.com.tr/ekonomi/bayram-tatilinde-akaryakit-talebi-zirve-yapti-motorine-347-milyar-benzine-ise-129-milyar-tl-harcandi-7553443",
      "published_date": "2026-03-30T10:03:14Z",
      "category": "Energy"
    },
    {
      "title": "Dollar is at its highest level in the last 10 months",
      "source": "Haberturk",
      "url": "https://www.haberturk.com/dolar-ortadogu-da-tansiyonun-yukselmesiyle-son-10-ayin-zirvesinde-3873394-ekonomi",
      "published_date": "2026-03-30T09:27:09Z",
      "category": "Energy"
    },
    {
      "title": "Solid fuel engine tested in North Korea",
      "source": "Sabah",
      "url": "https://www.sabah.com.tr/dunya/kuzey-korede-kati-yakitli-motor-test-edildi-7553388",
      "published_date": "2026-03-30T08:39:45Z",
      "category": "Energy"
    },
    {
      "title": "Trump wants Iranian oil: Seizing Hark Island is among our options",
      "source": "Sabah",
      "url": "https://www.sabah.com.tr/dunya/trump-iran-petrolunu-istiyor-hark-adasini-ele-gecirmek-seceneklerimiz-arasinda-7553372",
      "published_date": "2026-03-30T08:21:21Z",
      "category": "Energy"
    },
    {
      "title": "Concern about the increase in flight tickets in the USA",
      "source": "Haberturk",
      "url": "https://www.haberturk.com/abd-de-yakit-fiyatlarinin-artmasinin-ucak-biletlerini-ve-sefer-sayilarini-etkileyecegi-uyarisi-3873355-ekonomi",
      "published_date": "2026-03-30T07:17:13Z",
      "category": "Energy"
    },
    {
      "title": "Global markets started the week negatively",
      "source": "Haberturk",
      "url": "https://www.haberturk.com/kuresel-piyasalar-haftaya-negatif-basladi-3873332-ekonomi",
      "published_date": "2026-03-30T06:29:32Z",
      "category": "Energy"
    },
    {
      "title": "Minister Kurum: \"A more just world is possible with zero waste\"",
      "source": "Sabah",
      "url": "https://www.sabah.com.tr/gundem/2026/03/29/bakan-kurum-daha-adil-bir-dunya-sifir-atik-ile-mumkun",
      "published_date": "2026-03-29T20:07:38Z",
      "category": "Energy"
    },
    {
      "title": "Energy prices are upside down! Oil, gas and coal prices rose sharply",
      "source": "Sabah",
      "url": "https://www.sabah.com.tr/ekonomi/enerji-fiyatlari-tepe-taklak-petrol-gaz-ve-komur-fiyatlari-sert-yukseldi-7552938",
      "published_date": "2026-03-29T13:55:17Z",
      "category": "Energy"
    },
    {
      "title": "List of flights canceled on March 29",
      "source": "Haberturk",
      "url": "https://www.haberturk.com/sabiha-gokcen-iptal-olan-ucuslar-listesi-29-mart-2026-thy-pegasus-ajet-ucak-seferleri-iptal-mi-hangi-ucuslar-iptal-oldu-iptal-ucak-seferi-sorgulama-3873228",
      "published_date": "2026-03-29T12:47:53Z",
      "category": "Energy"
    },
    {
      "title": "Are Türkiye's natural gas stocks ready for a shock? Minister Bayraktar announced the occupancy rate",
      "source": "Sabah",
      "url": "https://www.sabah.com.tr/ekonomi/turkiyenin-dogal-gaz-stoklari-soka-hazir-mi-bakan-bayraktar-doluluk-oranini-acikladi-7552843",
      "published_date": "2026-03-29T09:52:38Z",
      "category": "Energy"
    },
    {
      "title": "Ethical exam of artificial intelligence",
      "source": "Haberturk",
      "url": "https://www.haberturk.com/veri-merkezlerinin-su-ve-enerji-tuketimi-ekolojik-surdurulebilirligi-tehdit-ediyor-3873201-teknoloji",
      "published_date": "2026-03-29T09:47:37Z",
      "category": "Energy"
    },
    {
      "title": "\"Our natural gas tanks are 71 percent full\"",
      "source": "Haberturk",
      "url": "https://www.haberturk.com/dogal-gaz-depolarimiz-yuzde-71-dolu-3873200-ekonomi",
      "published_date": "2026-03-29T09:42:06Z",
      "category": "Energy"
    },
    {
      "title": "Goal is to expand abroad",
      "source": "Haberturk",
      "url": "https://www.haberturk.com/hedefi-yurt-disina-acilmak-3873187-ekonomi",
      "published_date": "2026-03-29T09:06:06Z",
      "category": "Energy"
    },
    {
      "title": "No more surprises, everything will be written clearly! Details of the new era in restaurants and cafes have been announced",
      "source": "Sabah",
      "url": "https://www.sabah.com.tr/ekonomi/surprize-son-her-sey-acik-acik-yazacak-restoran-ve-kafelerde-yeni-donemin-ayrintilari-belli-oldu-7552801",
      "published_date": "2026-03-29T08:27:00Z",
      "category": "Energy"
    },
    {
      "title": "Fuel crisis measure in Australia: Public transport became free in two states",
      "source": "Sabah",
      "url": "https://www.sabah.com.tr/ekonomi/avustralyada-yakit-krizi-onlemi-iki-eyalette-toplu-tasima-ucretsiz-oldu-7552793",
      "published_date": "2026-03-29T08:06:12Z",
      "category": "Energy"
    },
    {
      "title": "Huge increase in diesel price!",
      "source": "Haberturk",
      "url": "https://www.haberturk.com/motorine-dev-zam-geldi-29-mart-2026-pazar-istanbul-ankara-izmir-motorinin-litre-fiyati-ne-kadar-oldu-3872987",
      "published_date": "2026-03-28T21:08:53Z",
      "category": "Energy"
    },
    {
      "title": "'We will not be the ones to add fuel to the fire of discord'",
      "source": "Haberturk",
      "url": "https://www.haberturk.com/mit-baskani-ibrahim-kalin-biz-turkiye-olarak-hicbir-zaman-fitne-atesine-odun-tasiyan-taraf-olmayacagiz-3873065",
      "published_date": "2026-03-28T14:10:23Z",
      "category": "Energy"
    },
    {
      "title": "Iran: The market is numb",
      "source": "Haberturk",
      "url": "https://www.haberturk.com/iran-meclis-baskani-kalibaf-piyasa-uyustu-3872972-ekonomi",
      "published_date": "2026-03-27T22:33:00Z",
      "category": "Energy"
    },
    {
      "title": "3 billion TL interest-free financing will be provided through development agencies",
      "source": "Haberturk",
      "url": "https://www.haberturk.com/kalkinma-ajanslariyla-3-milyar-tl-faizsiz-finansman-saglanacak-3873469-ekonomi",
      "published_date": "2026-03-30T13:36:30Z",
      "category": "Economy"
    },
    {
      "title": "Change in bread and flour regulation! Which substances are banned?",
      "source": "Sabah",
      "url": "https://www.sabah.com.tr/ekonomi/ekmek-ve-un-yonetmeliginde-degisiklik-hangi-maddeler-yasaklandi-7553500",
      "published_date": "2026-03-30T13:03:26Z",
      "category": "Economy"
    },
    {
      "title": "New increase in packages from Netflix",
      "source": "Haberturk",
      "url": "https://www.haberturk.com/netflixten-aboneliklere-yeni-zam-tum-abonelik-planlari-zamlandi-fiyatlar-yukseldi-3873470-teknoloji",
      "published_date": "2026-03-30T12:50:07Z",
      "category": "Economy"
    },
    {
      "title": "Thanks to employees on the occasion of 5G signal",
      "source": "Haberturk",
      "url": "https://www.haberturk.com/turkcell-yonetim-kurulu-baskani-senol-kazancidan-5g-mesaji-5g-sinyali-vesilesiyle-calisanlara-tesekkur-3873452-teknoloji",
      "published_date": "2026-03-30T11:54:37Z",
      "category": "Economy"
    },
    {
      "title": "Hawkish expectation from central banks: When will the CBRT interest rate decision be announced?",
      "source": "Sabah",
      "url": "https://www.sabah.com.tr/ekonomi/merkez-bankalarindan-sahin-beklenti-tcmb-faiz-karari-ne-zaman-aciklanacak-7553445",
      "published_date": "2026-03-30T10:06:25Z",
      "category": "Economy"
    },
    {
      "title": "Nearly 20.9 million transactions were made in the Digital Tax Office last year",
      "source": "Sabah",
      "url": "https://www.sabah.com.tr/ekonomi/dijital-vergi-dairesinde-gecen-yil-209-milyona-yakin-islem-yapildi-7553438",
      "published_date": "2026-03-30T09:56:25Z",
      "category": "Economy"
    },
    {
      "title": "Warning from experts: Do not turn your home into an investment tool",
      "source": "Haberturk",
      "url": "https://www.haberturk.com/uzmanlardan-uyari-evinizi-yatirim-araci-yapmayin-3873402-ekonomi",
      "published_date": "2026-03-30T09:28:34Z",
      "category": "Economy"
    },
    {
      "title": "Maternity allowance payments have started",
      "source": "Haberturk",
      "url": "https://www.haberturk.com/mart-ayi-dogum-yardim-odemeleri-annelerin-hesaplarina-yatirildi-3873376-ekonomi",
      "published_date": "2026-03-30T08:01:31Z",
      "category": "Economy"
    },
    {
      "title": "Stock market started the day with an increase",
      "source": "Haberturk",
      "url": "https://www.haberturk.com/borsa-haftaya-yukselisle-basladi-3873361-ekonomi",
      "published_date": "2026-03-30T07:24:21Z",
      "category": "Economy"
    },
    {
      "title": "Decline in economic confidence",
      "source": "Haberturk",
      "url": "https://www.haberturk.com/ekonomik-guven-endeksi-martta-aylik-yuzde-2-8-azalarak-97-9-oldu-3873364-ekonomi",
      "published_date": "2026-03-30T07:23:15Z",
      "category": "Economy"
    },
    {
      "title": "Tax loss was detected in cases",
      "source": "Haberturk",
      "url": "https://www.haberturk.com/hallerde-vergi-kaybi-tespit-edildi-3873359-ekonomi",
      "published_date": "2026-03-30T07:19:51Z",
      "category": "Economy"
    },
    {
      "title": "Latest situation in gold prices",
      "source": "Haberturk",
      "url": "https://www.haberturk.com/altin-fiyatlarinda-son-durum-3873346-ekonomi",
      "published_date": "2026-03-30T06:55:16Z",
      "category": "Economy"
    },
    {
      "title": "Property tax guide for retirees",
      "source": "Haberturk",
      "url": "https://www.haberturk.com/emekliler-icin-emlak-vergisi-rehberi-3873248-ekonomi",
      "published_date": "2026-03-30T04:32:53Z",
      "category": "Economy"
    },
    {
      "title": "Current gold prices",
      "source": "Haberturk",
      "url": "https://www.haberturk.com/guncel-altin-fiyatlari-30-mart-2026-bugun-altin-fiyatlari-ne-kadar-kac-tl-iste-14-ve-22-ayar-bilezik-cumhuriyet-tam-yarim-ceyrek-ve-gram-altin-fiyatlari-3873142",
      "published_date": "2026-03-29T21:10:14Z",
      "category": "Economy"
    },
    {
      "title": "Denial of CHP's claims from the Ministry of Commerce: \"Trade with Israel is zero\"",
      "source": "Sabah",
      "url": "https://www.sabah.com.tr/ekonomi/ticaret-bakanligindan-chpnin-iddialarina-yalanlama-israil-ile-ticaret-sifirdir-7552972",
      "published_date": "2026-03-29T16:18:47Z",
      "category": "Economy"
    },
    {
      "title": "Ministry of Commerce: Trade with Israel is zero",
      "source": "Haberturk",
      "url": "https://www.haberturk.com/ticaret-bakanligi-israil-ile-ticaret-sifir-3873260-ekonomi",
      "published_date": "2026-03-29T15:51:16Z",
      "category": "Economy"
    },
    {
      "title": "Minister Kacır: Being strong is possible with technology capabilities",
      "source": "Sabah",
      "url": "https://www.sabah.com.tr/gundem/2026/03/29/bakan-kacir-kuvvetli-olmak-teknoloji-kabiliyetleriyle-mumkun",
      "published_date": "2026-03-29T14:48:42Z",
      "category": "Economy"
    },
    {
      "title": "All eyes on the July price hike!",
      "source": "Haberturk",
      "url": "https://www.haberturk.com/memur-ve-emekli-temmuz-zammi-hesaplama-2026-temmuz-emekli-zammi-ve-memur-zammi-ne-kadar-olacak-3873247",
      "published_date": "2026-03-29T14:17:32Z",
      "category": "Economy"
    },
    {
      "title": "Current interest rates for a loan of 100 thousand TL",
      "source": "Haberturk",
      "url": "https://www.haberturk.com/100-bin-tl-lik-ihtiyac-kredisinin-geri-odemesi-ne-kadar-faiz-orani-yuzde-kac-aylik-ve-toplam-taksit-tutari-ne-kadar-3873242",
      "published_date": "2026-03-29T13:51:56Z",
      "category": "Economy"
    },
    {
      "title": "All eyes in the markets are on inflation, foreign trade and interest! Here is the April agenda in the economy",
      "source": "Sabah",
      "url": "https://www.sabah.com.tr/ekonomi/piyasalarda-gozler-enflasyon-dis-ticaret-ve-faizde-iste-ekonomide-nisan-ajandasi-7552857",
      "published_date": "2026-03-29T10:31:56Z",
      "category": "Economy"
    },
    {
      "title": "The investigation into the \"Hats\" gang has been completed! Bloody actions in indictment: Blackmail to businessman with honey trap",
      "source": "Sabah",
      "url": "https://www.sabah.com.tr/yasam/sapkalilar-cetesine-yonelik-sorusturma-tamamlandi-kanli-eylemler-iddianamede-is-adamina-bal-tuzakli-santaj-7553520",
      "published_date": "2026-03-30T14:09:44Z",
      "category": "Local Events"
    },
    {
      "title": "Critical meeting from Minister Ersoy: Türkiye is strengthening its preparations against global risks",
      "source": "Sabah",
      "url": "https://www.sabah.com.tr/ekonomi/bakan-ersoydan-kritik-toplanti-kuresel-risklere-karsi-turkiye-hazirliklarini-guclendiriyor-7553517",
      "published_date": "2026-03-30T14:05:55Z",
      "category": "Local Events"
    },
    {
      "title": "Remarkable move from Spain: Airspace is closed to US planes",
      "source": "Sabah",
      "url": "https://www.sabah.com.tr/dunya/ispanyadan-dikkat-ceken-hamle-hava-sahasi-abd-ucaklarina-kapatildi-7553516",
      "published_date": "2026-03-30T14:04:26Z",
      "category": "Local Events"
    },
    {
      "title": "Critical meeting from Minister Ersoy for 2026 tourism",
      "source": "Haberturk",
      "url": "https://www.haberturk.com/bakan-ersoy-dan-2026-turizmi-icin-kritik-toplanti-3873483-ekonomi",
      "published_date": "2026-03-30T13:42:34Z",
      "category": "Local Events"
    },
    {
      "title": "NASA updated the Artemis Program",
      "source": "Haberturk",
      "url": "https://www.haberturk.com/nasanin-artemis-programi-apollodan-gunumuze-insanli-ay-misyonunun-kritik-donum-noktalari-3873477-teknoloji",
      "published_date": "2026-03-30T13:39:38Z",
      "category": "Local Events"
    },
    {
      "title": "5G Message from Turkcell Chairman Şenol Kazancı",
      "source": "Sabah",
      "url": "https://www.sabah.com.tr/ekonomi/turkcell-yonetim-kurulu-baskani-senol-kazancidan-5g-mesaji-7553498",
      "published_date": "2026-03-30T12:49:17Z",
      "category": "Local Events"
    },
    {
      "title": "Health insurance tailored to your needs",
      "source": "Haberturk",
      "url": "https://www.haberturk.com/turkiye-sigortadan-esnek-saglik-sigortasi-3873464-ekonomi",
      "published_date": "2026-03-30T12:29:40Z",
      "category": "Local Events"
    },
    {
      "title": "BREAKING NEWS: CHP member was harassed by Görele Mayor! Sad news came from the young girl who had a traffic accident",
      "source": "Sabah",
      "url": "https://www.sabah.com.tr/yasam/son-dakika-chpli-gorele-belediye-baskani-tarafindan-taciz-edilmisti-trafik-kazasi-geciren-genc-kizdan-aci-haber-geldi-7553482",
      "published_date": "2026-03-30T11:58:31Z",
      "category": "Local Events"
    },
    {
      "title": "Moved export credit to digital",
      "source": "Haberturk",
      "url": "https://www.haberturk.com/ihracat-kredisini-dijitale-tasidi-3873453-ekonomi",
      "published_date": "2026-03-30T11:56:40Z",
      "category": "Local Events"
    },
    {
      "title": "5G signal in 81 provinces and 922 districts",
      "source": "Haberturk",
      "url": "https://www.haberturk.com/81-il-ve-922-ilcede-5g-sinyali-vodafone-engin-aksoy-5gde-almanyanin-5-yilda-geldigi-noktaya-ilk-gunden-ulasacagiz-3873439-teknoloji",
      "published_date": "2026-03-30T11:32:07Z",
      "category": "Local Events"
    },
    {
      "title": "An area the size of 55 thousand football fields was protected! Great success in recycling with 'zero waste'",
      "source": "Sabah",
      "url": "https://www.sabah.com.tr/ekonomi/55-bin-futbol-sahasi-buyuklugunde-alan-korundu-sifir-atik-ile-geri-kazanimda-buyuk-basari-7553452",
      "published_date": "2026-03-30T10:27:08Z",
      "category": "Local Events"
    },
    {
      "title": "'Zero Waste' post from President Erdoğan: It has turned into a global environmental movement!",
      "source": "Sabah",
      "url": "https://www.sabah.com.tr/gundem/2026/03/30/cumhurbaskani-erdogandan-sifir-atik-paylasimi",
      "published_date": "2026-03-30T09:49:10Z",
      "category": "Local Events"
    },
    {
      "title": "'Spying' accusation against British diplomat in Russia: He is being deported from the country",
      "source": "Sabah",
      "url": "https://www.sabah.com.tr/dunya/rusyada-ingiliz-diplomatina-casusluk-suclamasi-ulkeden-sinir-disi-ediliyor-7553417",
      "published_date": "2026-03-30T09:20:32Z",
      "category": "Local Events"
    },
    {
      "title": "Statement from the Ministry of Internal Affairs: Fake license plate fine is at the door!",
      "source": "Sabah",
      "url": "https://www.sabah.com.tr/gundem/2026/03/30/icisleri-bakanligindan-aciklama-geldi-sahte-plaka-cezasi-kapida",
      "published_date": "2026-03-30T09:16:37Z",
      "category": "Local Events"
    },
    {
      "title": "License plate statement from the ministry",
      "source": "Haberturk",
      "url": "https://www.haberturk.com/icisleri-bakanligi-ndan-plaka-aciklamasi-3873396-ekonomi",
      "published_date": "2026-03-30T09:08:16Z",
      "category": "Local Events"
    },
    {
      "title": "A product that goes beyond the norm in healthcare from Türkiye Sigorta: ESS",
      "source": "Sabah",
      "url": "https://www.sabah.com.tr/ekonomi/turkiye-sigortadan-saglikta-kaliplarin-disina-cikan-urun-ess-7553406",
      "published_date": "2026-03-30T09:03:22Z",
      "category": "Local Events"
    },
    {
      "title": "Building collapsed in China: 7 dead",
      "source": "Sabah",
      "url": "https://www.sabah.com.tr/dunya/cinde-bina-yerle-bir-oldu-7-olu-7553397",
      "published_date": "2026-03-30T08:48:54Z",
      "category": "Local Events"
    },
    {
      "title": "Condolence message from Kurtulmuş to the martyred police officer",
      "source": "Sabah",
      "url": "https://www.sabah.com.tr/gundem/2026/03/30/kurtulmustan-sehit-olan-polis-memuru-icin-bassagligi-mesaji",
      "published_date": "2026-03-30T07:58:23Z",
      "category": "Local Events"
    },
    {
      "title": "Mansur Yavaş is at the top of the concert pyramid: Exorbitant payments have been approved!",
      "source": "Sabah",
      "url": "https://www.sabah.com.tr/yasam/konser-piramidinin-zirvesinde-mansu-yavas-var-daire-baskaninin-whatsapp-mesajlari-ortaya-cikti-7553293",
      "published_date": "2026-03-30T07:26:24Z",
      "category": "Local Events"
    },
    {
      "title": "Flights returned to normal at Sabiha Gökçen",
      "source": "Haberturk",
      "url": "https://www.haberturk.com/sabiha-gokcen-de-ucuslar-normale-dondu-3873344-ekonomi",
      "published_date": "2026-03-30T06:53:22Z",
      "category": "Local Events"
    }
  ]
}