{
  "country": "turkey",
  "last_updated": "2026-06-15T00:07:17Z",
  "stories": [
    {
      "title": "Sharing from Director of Communications Duran regarding the US-Iran peace agreement",
      "source": "Sabah",
      "url": "https://www.sabah.com.tr/gundem/2026/06/14/iletisim-baskani-durandan-abd-iran-baris-anlasmasina-iliskin-paylasim",
      "published_date": "2026-06-14T23:59:07Z",
      "category": "Diplomacy"
    },
    {
      "title": "BREAKING NEWS I President Erdoğan's call for peace and stability: \"We will continue to contribute to permanent solutions\"",
      "source": "Sabah",
      "url": "https://www.sabah.com.tr/gundem/2026/06/14/son-dakika-i-baskan-erdogandan-baris-ve-istikrar-cagrisi-kalici-cozumlere-katki-sunmaya-devam-edecegiz",
      "published_date": "2026-06-14T23:27:08Z",
      "category": "Diplomacy"
    },
    {
      "title": "BREAKING NEWS I Peace message from Minister Fidan: \"We welcome the agreement between the USA and Iran\"",
      "source": "Sabah",
      "url": "https://www.sabah.com.tr/gundem/2026/06/14/son-dakika-i-bakan-fidandan-baris-mesaji-abd-ile-iran-arasindaki-mutabakati-memnuniyetle-karsiliyoruz",
      "published_date": "2026-06-14T23:12:06Z",
      "category": "Diplomacy"
    },
    {
      "title": "The election victory of the party led by Pashinyan in Armenia has been confirmed",
      "source": "Sabah",
      "url": "https://www.sabah.com.tr/dunya/ermenistanda-pasinyanin-liderligindeki-partinin-secim-galibiyeti-kesinlesti-7603050",
      "published_date": "2026-06-14T17:43:24Z",
      "category": "Diplomacy"
    },
    {
      "title": "Meta terminates $2 billion Manus deal",
      "source": "Haberturk",
      "url": "https://www.haberturk.com/meta-pekinin-talebiyle-2-milyar-dolarlik-manus-anlasmasini-feshediyor-3891567-teknoloji",
      "published_date": "2026-06-14T10:40:41Z",
      "category": "Diplomacy"
    },
    {
      "title": "Famous wind in Didim",
      "source": "Haberturk",
      "url": "https://www.haberturk.com/didim-de-unlu-ruzgari-magazin-haberleri-3891546-magazin",
      "published_date": "2026-06-14T08:59:42Z",
      "category": "Diplomacy"
    },
    {
      "title": "Markets focused on FED decision: Oil fell, gold is under pressure",
      "source": "Sabah",
      "url": "https://www.sabah.com.tr/ekonomi/piyasalar-fed-kararina-odaklandi-petrol-dustu-altin-baski-altinda-7602853",
      "published_date": "2026-06-14T08:49:37Z",
      "category": "Diplomacy"
    },
    {
      "title": "When is the Türkiye - Paraguay match?",
      "source": "Haberturk",
      "url": "https://www.haberturk.com/turkiye-dunya-kupasi-2-maci-turkiye-paraguay-maci-ne-zaman-saat-kacta-hangi-kanalda-3891538",
      "published_date": "2026-06-14T07:59:39Z",
      "category": "Diplomacy"
    },
    {
      "title": "mother-daughter holiday",
      "source": "Haberturk",
      "url": "https://www.haberturk.com/serenay-sarikaya-annesi-umran-seyhan-ile-tatile-cikti-magazin-haberleri-3891466-magazin",
      "published_date": "2026-06-14T07:30:33Z",
      "category": "Diplomacy"
    },
    {
      "title": "Trump: Hormuz will be opened to everyone after the agreement",
      "source": "Sabah",
      "url": "https://www.sabah.com.tr/ekonomi/trump-anlasma-sonrasi-hurmuz-herkese-acilacak-7602780",
      "published_date": "2026-06-14T06:27:17Z",
      "category": "Diplomacy"
    },
    {
      "title": "BREAKING NEWS| US President Trump: US-Iran agreement signed!",
      "source": "Sabah",
      "url": "https://www.sabah.com.tr/dunya/canli-son-dakika-abd-iran-barisi-icin-geri-sayim-olasi-anlasma-israili-endiselendirdi-tahran-yonetimi-guclenecek-7602768",
      "published_date": "2026-06-14T06:12:03Z",
      "category": "Diplomacy"
    },
    {
      "title": "We produce our own technologies",
      "source": "Sabah",
      "url": "https://www.sabah.com.tr/gundem/2026/06/14/teknolojilerimizi-kendimiz-uretiyoruz",
      "published_date": "2026-06-14T03:53:54Z",
      "category": "Diplomacy"
    },
    {
      "title": "Record temperatures in Antarctica are frightening",
      "source": "Sabah",
      "url": "https://www.sabah.com.tr/dunya/antarktikada-rekor-sicakliklar-korkutuyor-7602555",
      "published_date": "2026-06-14T03:53:54Z",
      "category": "Diplomacy"
    },
    {
      "title": "Trump shock in Israel",
      "source": "Sabah",
      "url": "https://www.sabah.com.tr/yazarlar/bercan-tutar/2026/06/14/israildeki-trump-soku",
      "published_date": "2026-06-14T03:53:54Z",
      "category": "Diplomacy"
    },
    {
      "title": "Armed attack on KADES report: 3 seriously injured, including a police officer",
      "source": "Haberturk",
      "url": "https://www.haberturk.com/mugla-da-kades-ihbarina-silahli-saldiri-1-i-polis-3-agir-yarali-3891490",
      "published_date": "2026-06-13T23:59:29Z",
      "category": "Diplomacy"
    },
    {
      "title": "Official Gazette decisions 14 June",
      "source": "Haberturk",
      "url": "https://www.haberturk.com/resmi-gazete-kararlari-14-haziran-2026-bugunku-resmi-gazete-yayimlandi-mi-alinan-kararlari-neler-3891485",
      "published_date": "2026-06-13T21:47:05Z",
      "category": "Diplomacy"
    },
    {
      "title": "Did an earthquake just happen?",
      "source": "Haberturk",
      "url": "https://www.haberturk.com/az-once-deprem-mi-oldu-14-haziran-pazar-afad-kandilli-son-dakika-depremler-listesi-3891348",
      "published_date": "2026-06-13T21:05:40Z",
      "category": "Diplomacy"
    },
    {
      "title": "Mine operation in the Strait of Hormuz! US President Trump's G-7 Summit plan revealed",
      "source": "Sabah",
      "url": "https://www.sabah.com.tr/dunya/hurmuz-bogazinda-mayin-operasyonu-abd-baskani-trumpin-g-7-zirvesi-plani-ortaya-cikti-7602401",
      "published_date": "2026-06-13T16:17:41Z",
      "category": "Diplomacy"
    },
    {
      "title": "Important partnership from Monopoli Sigorta",
      "source": "Haberturk",
      "url": "https://www.haberturk.com/monopoli-sigorta-dan-onemli-ortaklik-3891447-ekonomi",
      "published_date": "2026-06-13T16:11:21Z",
      "category": "Diplomacy"
    },
    {
      "title": "The winner of the summit has been announced!",
      "source": "Haberturk",
      "url": "https://www.haberturk.com/reytinglerde-surpriz-sonuc-zirvenin-sahibi-belli-oldu-12-haziran-reytingleri-aciklandi-3891371",
      "published_date": "2026-06-13T14:36:55Z",
      "category": "Diplomacy"
    },
    {
      "title": "Pakistan announced that an agreement was reached between the USA and Iran",
      "source": "Sabah",
      "url": "https://www.sabah.com.tr/dunya/pakistan-abd-ve-iran-arasinda-anlasmaya-varildigini-duyurdu-7603178",
      "published_date": "2026-06-14T21:59:21Z",
      "category": "Military"
    },
    {
      "title": "Minister Çiftçi addressed the Gendarmerie over the radio: You have an indelible place in the hearts of our nation.",
      "source": "Sabah",
      "url": "https://www.sabah.com.tr/gundem/2026/06/14/bakan-ciftci-telsizden-jandarma-teskilatina-seslendi-milletimizin-gonlunde-silinmez-bir-yere-sahipsiniz",
      "published_date": "2026-06-14T15:25:18Z",
      "category": "Military"
    },
    {
      "title": "Alarm in the US army: F/A-18 fighter plane crashed! 12 people lost their lives",
      "source": "Sabah",
      "url": "https://www.sabah.com.tr/dunya/abd-ordusunda-alarm-fa-18-savas-ucagi-dustu-7602968",
      "published_date": "2026-06-14T14:14:17Z",
      "category": "Military"
    },
    {
      "title": "AK Party Spokesperson Ömer Çelik's reaction to AP Akın Gürlek: We reject his targeting of Turkey with 'political bigotry'",
      "source": "Sabah",
      "url": "https://www.sabah.com.tr/gundem/2026/06/14/ak-parti-sozcusu-omer-celikten-apyeakin-gurlek-tepkisi-siyasi-yobazlikla-turkiyeyi-hedef-almasini-reddediyoruz",
      "published_date": "2026-06-14T12:36:17Z",
      "category": "Military"
    },
    {
      "title": "Britain stops oil tanker belonging to Russia's \"shadow fleet\"",
      "source": "Sabah",
      "url": "https://www.sabah.com.tr/ekonomi/ingiltere-rusyanin-golge-filosuna-ait-petrol-tankerini-durdurdu-7602859",
      "published_date": "2026-06-14T09:09:47Z",
      "category": "Military"
    },
    {
      "title": "How to adjust TRT frequency?",
      "source": "Haberturk",
      "url": "https://www.haberturk.com/trt-1-guncel-frekans-ayarlari-2026-dunya-kupasi-maclari-trt-frekans-ayari-nasil-yapilir-trt-1-sinyal-yok-hatasi-nasil-cozulur-3891472",
      "published_date": "2026-06-14T08:07:20Z",
      "category": "Military"
    },
    {
      "title": "Will peace be achieved on the US-Iran line?",
      "source": "Haberturk",
      "url": "https://www.haberturk.com/abd-iran-hattinda-baris-saglanacak-mi-3891519",
      "published_date": "2026-06-14T08:06:46Z",
      "category": "Military"
    },
    {
      "title": "1 billion operation: 32 arrests",
      "source": "Haberturk",
      "url": "https://www.haberturk.com/son-dakika-tekirdag-ve-istanbul-da-duzenlenen-yasa-disi-bahis-operasyonunda-32-tutuklama-3891532",
      "published_date": "2026-06-14T07:39:10Z",
      "category": "Military"
    },
    {
      "title": "Dangerous tension in the English Channel: Britain seized the Russian oil tanker",
      "source": "Sabah",
      "url": "https://www.sabah.com.tr/dunya/mans-denizinde-tehlikeli-gerilim-ingiltere-rus-petrol-tankerini-ele-gecirdi-7602819",
      "published_date": "2026-06-14T07:31:02Z",
      "category": "Military"
    },
    {
      "title": "Military transport plane crashed in India: 5 dead",
      "source": "Sabah",
      "url": "https://www.sabah.com.tr/dunya/hindistanda-askeri-nakliye-ucagi-yere-cakildi-5-olu-7602810",
      "published_date": "2026-06-14T07:17:15Z",
      "category": "Military"
    },
    {
      "title": "\"If you had stolen it, I would have picked it up\" defense",
      "source": "Haberturk",
      "url": "https://www.haberturk.com/son-dakika-bursa-da-firariden-sok-eden-savunma-yakalaninca-calsaydiniz-acardim-dedi-3891521",
      "published_date": "2026-06-14T06:45:45Z",
      "category": "Military"
    },
    {
      "title": "12 must-see bays of Bodrum",
      "source": "Haberturk",
      "url": "https://www.haberturk.com/biri-maldivleri-andiriyor-birinde-sicak-su-magarasi-var-bodrumun-mutlaka-gorulmesi-gereken-12-koyu-3890717",
      "published_date": "2026-06-14T06:23:07Z",
      "category": "Military"
    },
    {
      "title": "Attack on food factory: cook died",
      "source": "Haberturk",
      "url": "https://www.haberturk.com/kastamonu-da-yemek-fabrikasina-silahli-saldirida-asci-oldu-3891493",
      "published_date": "2026-06-14T05:57:34Z",
      "category": "Military"
    },
    {
      "title": "3 injured in bear attack",
      "source": "Haberturk",
      "url": "https://www.haberturk.com/tunceli-de-mantar-toplayanlara-ayi-saldirdi-3-yarali-3891496",
      "published_date": "2026-06-14T05:56:19Z",
      "category": "Military"
    },
    {
      "title": "Syrian President Shara denies the allegation of \"intervention in Lebanon\"",
      "source": "Sabah",
      "url": "https://www.sabah.com.tr/dunya/suriye-cumhurbaskani-saradan-lubnana-mudahale-iddiasina-yalanlama-7602462",
      "published_date": "2026-06-13T17:55:09Z",
      "category": "Military"
    },
    {
      "title": "Call from Selçuk Bayraktar to friendly and brotherly countries: We have to unite our strength",
      "source": "Sabah",
      "url": "https://www.sabah.com.tr/gundem/2026/06/13/selcuk-bayraktardan-dost-ve-kardes-ulkelere-cagri-gucumuzu-birlestirmek-zorundayiz",
      "published_date": "2026-06-13T16:30:37Z",
      "category": "Military"
    },
    {
      "title": "A Lebanese soldier was seriously injured in an Israeli army drone attack",
      "source": "Sabah",
      "url": "https://www.sabah.com.tr/dunya/israil-ordusunun-iha-saldirisinda-bir-lubnan-askeri-agir-yaralandi-7602324",
      "published_date": "2026-06-13T14:05:03Z",
      "category": "Military"
    },
    {
      "title": "There are doctors among them! 13 arrests for fake report!",
      "source": "Haberturk",
      "url": "https://www.haberturk.com/son-dakika-haberi-aralarinda-doktorlar-var-150-bin-tl-karsiliginda-sahte-rapora-13-tutuklama-3891400",
      "published_date": "2026-06-13T12:43:40Z",
      "category": "Military"
    },
    {
      "title": "A first in Pompeii after 20 years",
      "source": "Haberturk",
      "url": "https://www.haberturk.com/pompei-de-20-yil-sonra-bir-ilk-3891407",
      "published_date": "2026-06-13T12:21:33Z",
      "category": "Military"
    },
    {
      "title": "He killed his pregnant wife and his uncle... \"Random\" massacre!",
      "source": "Haberturk",
      "url": "https://www.haberturk.com/son-dakika-haberi-hamile-esi-ve-amcasini-oldurmustu-rastgele-katliam-siirt-haberleri-3891356",
      "published_date": "2026-06-13T12:01:40Z",
      "category": "Military"
    },
    {
      "title": "Minister Kurum dived into the gulf with a scuba",
      "source": "Haberturk",
      "url": "https://www.haberturk.com/bakan-kurum-izmit-korfezi-ne-tuple-daldi-3891528",
      "published_date": "2026-06-14T11:35:39Z",
      "category": "Energy"
    },
    {
      "title": "Onshore wind energy will come to the fore in Europe",
      "source": "Haberturk",
      "url": "https://www.haberturk.com/avrupa-da-2030-a-kadar-yenilenebilir-kapasite-artislarinin-cogu-karasal-ruzgar-enerjisinden-olusacak-3891554-ekonomi",
      "published_date": "2026-06-14T09:46:52Z",
      "category": "Energy"
    },
    {
      "title": "Onshore wind energy will come to the fore in Europe",
      "source": "Sabah",
      "url": "https://www.sabah.com.tr/ekonomi/avrupada-karasal-ruzgar-enerjisi-on-plana-cikacak-7602834",
      "published_date": "2026-06-14T08:11:35Z",
      "category": "Energy"
    },
    {
      "title": "Minister Kurum dived into Izmit Bay with scuba",
      "source": "Sabah",
      "url": "https://www.sabah.com.tr/ekonomi/bakan-kurum-izmit-korfezine-tuple-daldi-7602798",
      "published_date": "2026-06-14T07:00:00Z",
      "category": "Energy"
    },
    {
      "title": "When will Beta Energy and Technology go public?",
      "source": "Haberturk",
      "url": "https://www.haberturk.com/beta-enerji-ve-teknoloji-halka-arz-ne-zaman-kac-lot-verir-hangi-bankalarda-var-beta-enerji-katilim-endeksine-uygun-mu-3891280",
      "published_date": "2026-06-12T21:44:28Z",
      "category": "Energy"
    },
    {
      "title": "Minister Bayraktar announced: TANAP transported 99 billion cubic meters of natural gas",
      "source": "Sabah",
      "url": "https://www.sabah.com.tr/ekonomi/bakan-bayraktar-acikladi-tanap-99-milyar-metrekup-dogal-gaz-tasidi-7601627",
      "published_date": "2026-06-12T12:41:31Z",
      "category": "Energy"
    },
    {
      "title": "How much are gasoline and diesel prices today?",
      "source": "Haberturk",
      "url": "https://www.haberturk.com/benzin-ve-motorin-fiyatlari-bugun-ne-kadar-benzin-ve-motorine-zam-ya-da-indirim-var-mi-brent-petrol-fiyati-ne-kadar-12-haziran-2026-guncel-akaryakit-fiyatlari-3890994",
      "published_date": "2026-06-12T11:16:22Z",
      "category": "Energy"
    },
    {
      "title": "It was once worth gold",
      "source": "Haberturk",
      "url": "https://www.haberturk.com/bir-zamanlar-altin-degerindeydi-simdi-yalniz-bir-ilimizde-hasat-ediliyor-haberturk-yasam-3891171",
      "published_date": "2026-06-12T10:01:08Z",
      "category": "Energy"
    },
    {
      "title": "Sharp fall in oil prices",
      "source": "Haberturk",
      "url": "https://www.haberturk.com/brent-petrol-abd-iran-anlasmasi-umuduyla-sert-dustu-3891146-ekonomi",
      "published_date": "2026-06-12T08:35:24Z",
      "category": "Energy"
    },
    {
      "title": "Soil and land regulation was accepted",
      "source": "Haberturk",
      "url": "https://www.haberturk.com/toprak-ve-arazi-duzenlemesi-tbmm-genel-kurulu-nda-kabul-edildi-3891057",
      "published_date": "2026-06-12T03:50:14Z",
      "category": "Energy"
    },
    {
      "title": "What is the subject of the 12 June Friday Sermon?",
      "source": "Haberturk",
      "url": "https://www.haberturk.com/cuma-hutbesi-konusu-12-haziran-cuma-hutbesi-konusu-nedir-istanbul-ankara-izmir-cuma-namazi-saat-kacta-3890959",
      "published_date": "2026-06-11T21:48:37Z",
      "category": "Energy"
    },
    {
      "title": "Strategic decision for fuel prices from EMRA! The period for national oil reserves has been extended",
      "source": "Sabah",
      "url": "https://www.sabah.com.tr/ekonomi/epdkdan-akaryakit-fiyatlari-icin-stratejik-karar-ulusal-petrol-rezervlerinde-sure-uzadi-7601028",
      "published_date": "2026-06-11T13:14:51Z",
      "category": "Energy"
    },
    {
      "title": "The fire in the mine has been going on for 6 days",
      "source": "Haberturk",
      "url": "https://www.haberturk.com/madendeki-yangin-6-gundur-suruyor-3890883",
      "published_date": "2026-06-11T07:40:32Z",
      "category": "Energy"
    },
    {
      "title": "US commercial crude oil stocks decreased",
      "source": "Haberturk",
      "url": "https://www.haberturk.com/abd-nin-ticari-ham-petrol-stoklari-azaldi-3890842-ekonomi",
      "published_date": "2026-06-11T05:48:15Z",
      "category": "Energy"
    },
    {
      "title": "Iran closes Strait of Hormuz, oil price rises",
      "source": "Haberturk",
      "url": "https://www.haberturk.com/iran-hurmuz-bogazi-ni-kapatti-petrol-fiyati-yukseldi-3890840-ekonomi",
      "published_date": "2026-06-11T05:21:35Z",
      "category": "Energy"
    },
    {
      "title": "Battery and energy storage base move from Peak PV",
      "source": "Haberturk",
      "url": "https://www.haberturk.com/peak-pv-den-panel-uretiminin-yanisira-batarya-ve-enerji-depolama-ussu-hamlesi-3890743-ekonomi",
      "published_date": "2026-06-10T14:22:59Z",
      "category": "Energy"
    },
    {
      "title": "2025 Global LNG Report: Trade volume reached record level with 428 million tons",
      "source": "Sabah",
      "url": "https://www.sabah.com.tr/ekonomi/2025-kuresel-lng-raporu-ticaret-hacmi-428-milyon-tonla-rekor-seviyeye-ulasti-7600148",
      "published_date": "2026-06-10T08:12:11Z",
      "category": "Energy"
    },
    {
      "title": "US raises oil price forecast",
      "source": "Haberturk",
      "url": "https://www.haberturk.com/abd-petrol-fiyati-tahminini-bu-yil-icin-yukseltti-3890607-ekonomi",
      "published_date": "2026-06-10T06:46:13Z",
      "category": "Energy"
    },
    {
      "title": "\"We aim for Türkiye to move into a new era in nuclear energy\"",
      "source": "Haberturk",
      "url": "https://www.haberturk.com/bakan-bayraktar-turkiye-nin-nukleer-enerjide-yeni-bir-doneme-gecmesini-hedefliyoruz-3890572-ekonomi",
      "published_date": "2026-06-10T04:23:32Z",
      "category": "Energy"
    },
    {
      "title": "Have the TTK draw results been announced?",
      "source": "Haberturk",
      "url": "https://www.haberturk.com/ttk-kura-sonuclari-sorgulama-ekrani-2026-turkiye-taskomuru-kurumu-262-isci-alimi-kura-cekimi-sonuclari-aciklandi-mi-isim-listesi-nasil-nereden-ogrenilir-3890410",
      "published_date": "2026-06-09T21:11:22Z",
      "category": "Energy"
    },
    {
      "title": "3 billion dollars of public resources for investments in artificial intelligence",
      "source": "Sabah",
      "url": "https://www.sabah.com.tr/ekonomi/yapay-zekaya-yatirimlarina-3-milyarlik-dolarlik-kamu-kaynagi-7602902",
      "published_date": "2026-06-14T11:00:10Z",
      "category": "Economy"
    },
    {
      "title": "Central banks week in markets",
      "source": "Haberturk",
      "url": "https://www.haberturk.com/kuresel-piyasalar-merkez-bankalari-haftasina-giriyor-3891424-ekonomi",
      "published_date": "2026-06-14T10:14:15Z",
      "category": "Economy"
    },
    {
      "title": "How much will the July retirement raise be?",
      "source": "Haberturk",
      "url": "https://www.haberturk.com/temmuz-2026-emekli-zammi-ne-kadar-olacak-6-aylik-enflasyon-farki-ile-ssk-bag-kur-en-dusuk-emekli-maas-zammi-hesaplama-3890955",
      "published_date": "2026-06-14T08:07:26Z",
      "category": "Economy"
    },
    {
      "title": "Politicians, academics and journalists spoke to SABAH after the Constitutional Court decision: \"The slanderers owe Berat Albayrak an apology.\"",
      "source": "Sabah",
      "url": "https://www.sabah.com.tr/ekonomi/aym-karari-sonrasi-siyasiler-akademisyenler-ve-gazeteciler-sabaha-konustu-iftiracilarin-berat-albayraka-ozur-borcu-var-7602456",
      "published_date": "2026-06-14T03:53:54Z",
      "category": "Economy"
    },
    {
      "title": "SpaceX's value exceeded 2 trillion dollars",
      "source": "Sabah",
      "url": "https://www.sabah.com.tr/ekonomi/spacexin-degeri-2-trilyon-dolari-gecti-7602428",
      "published_date": "2026-06-14T03:53:54Z",
      "category": "Economy"
    },
    {
      "title": "'Bilge' statement from TÜBİTAK",
      "source": "Haberturk",
      "url": "https://www.haberturk.com/tubitak-tan-bilge-aciklamasi-3891492-teknoloji",
      "published_date": "2026-06-13T23:09:56Z",
      "category": "Economy"
    },
    {
      "title": "How much will the civil servant salary be?",
      "source": "Haberturk",
      "url": "https://www.haberturk.com/memur-maasi-2026-temmuz-zammi-son-dakika-enflasyon-farki-ve-toplu-sozlesme-zammi-ile-memur-maasi-ne-kadar-olacak-memura-yuzde-kac-zam-gelir-3890257",
      "published_date": "2026-06-13T22:50:15Z",
      "category": "Economy"
    },
    {
      "title": "Current gold prices",
      "source": "Haberturk",
      "url": "https://www.haberturk.com/gram-altin-fiyati-14-haziran-2026-gram-altin-bugun-ne-kadar-altinda-yukselis-ivmesi-3891342",
      "published_date": "2026-06-13T21:05:57Z",
      "category": "Economy"
    },
    {
      "title": "Minister Kacır: We will make artificial intelligence the digital assurance of national sovereignty",
      "source": "Sabah",
      "url": "https://www.sabah.com.tr/gundem/2026/06/13/bakan-kacir-yapay-zekayi-milli-egemenligin-dijital-guvencesi-haline-getirecegiz",
      "published_date": "2026-06-13T16:36:24Z",
      "category": "Economy"
    },
    {
      "title": "Good news for fertilizer and diesel support for farmers! Minister Yumaklı announced, it will be recalculated",
      "source": "Sabah",
      "url": "https://www.sabah.com.tr/ekonomi/ciftcilere-gubre-ve-mazot-destegi-mujdesi-bakan-yumakli-duyurdu-yeniden-hesaplanacak-7602297",
      "published_date": "2026-06-13T13:05:46Z",
      "category": "Economy"
    },
    {
      "title": "Short selling ban extended",
      "source": "Haberturk",
      "url": "https://www.haberturk.com/aciga-satis-yasagi-uzatildi-3891408-ekonomi",
      "published_date": "2026-06-13T12:07:09Z",
      "category": "Economy"
    },
    {
      "title": "Short selling ban in the stock market has been extended until June 26",
      "source": "Sabah",
      "url": "https://www.sabah.com.tr/ekonomi/borsada-aciga-satis-yasagi-26-hazirana-kadar-uzatildi-7602271",
      "published_date": "2026-06-13T11:58:43Z",
      "category": "Economy"
    },
    {
      "title": "AK Party member Hüseyin Yayman: The issue of Türkiye without terrorism is a state and nation policy",
      "source": "Sabah",
      "url": "https://www.sabah.com.tr/gundem/2026/06/13/ak-partili-huseyin-yayman-terorsuz-turkiye-meselesi-bir-devlet-millet-politikasidir",
      "published_date": "2026-06-13T11:48:10Z",
      "category": "Economy"
    },
    {
      "title": "Türkiye's domestic and national artificial intelligence model: Bilge",
      "source": "Haberturk",
      "url": "https://www.haberturk.com/turkiyenin-yerli-ve-milli-yapay-zekasi-bakan-sordu-bilge-yanitladi-3891396-teknoloji",
      "published_date": "2026-06-13T11:20:17Z",
      "category": "Economy"
    },
    {
      "title": "Türkiye's local and national artificial intelligence model \"Bilge\" was showcased",
      "source": "Sabah",
      "url": "https://www.sabah.com.tr/ekonomi/turkiyenin-yerli-ve-milli-yapay-zeka-modeli-bilge-vitrine-cikti-7602228",
      "published_date": "2026-06-13T10:16:15Z",
      "category": "Economy"
    },
    {
      "title": "Domestic locomotive opened to the world market",
      "source": "Haberturk",
      "url": "https://www.haberturk.com/bakan-uraloglu-acikladi-yerli-lokomotif-dunya-pazarina-acildi-3891373-ekonomi",
      "published_date": "2026-06-13T09:18:12Z",
      "category": "Economy"
    },
    {
      "title": "600 million dollars of export from Türkiye! Here is the leading country",
      "source": "Sabah",
      "url": "https://www.sabah.com.tr/ekonomi/turkiyeden-600-milyon-dolar-ihracat-iste-basi-ceken-ulke-7602207",
      "published_date": "2026-06-13T09:11:44Z",
      "category": "Economy"
    },
    {
      "title": "Interest rate week in the markets! After CBRT, all eyes are on Fed President Warsh",
      "source": "Sabah",
      "url": "https://www.sabah.com.tr/ekonomi/piyasalarda-faiz-haftasi-gozler-tcmbden-sonra-fed-baskani-warshda-7602197",
      "published_date": "2026-06-13T08:37:31Z",
      "category": "Economy"
    },
    {
      "title": "Huge budget for Kenan Yıldız from Arsenal!",
      "source": "Haberturk",
      "url": "https://www.haberturk.com/arsenal-dan-kenan-yildiz-icin-dev-butce-arteta-nin-buyuk-hedefi-3891360-spor",
      "published_date": "2026-06-13T08:10:25Z",
      "category": "Economy"
    },
    {
      "title": "Current gold prices",
      "source": "Haberturk",
      "url": "https://www.haberturk.com/gram-altin-fiyati-13-haziran-2026-gram-altin-bugun-ne-kadar-altinda-yukselis-ivmesi-3891342",
      "published_date": "2026-06-13T07:00:36Z",
      "category": "Economy"
    },
    {
      "title": "Unmanned aerial vehicle found on the beach",
      "source": "Haberturk",
      "url": "https://www.haberturk.com/bartinda-sahilde-insansiz-hava-araci-bulundu-3891623",
      "published_date": "2026-06-14T20:29:50Z",
      "category": "Local Events"
    },
    {
      "title": "Plane carrying paratroopers crashed in the USA: 12 people died",
      "source": "Sabah",
      "url": "https://www.sabah.com.tr/dunya/abdde-parasutculeri-tasiyan-ucak-dustu-12-kisi-hayatini-kaybetti-7603142",
      "published_date": "2026-06-14T20:17:32Z",
      "category": "Local Events"
    },
    {
      "title": "Trump lashed out at Netanyahu: He has no judgment",
      "source": "Sabah",
      "url": "https://www.sabah.com.tr/dunya/trump-netanyahuya-ates-puskurdu-hicbir-muhakeme-yetenegi-yok-7603102",
      "published_date": "2026-06-14T18:44:11Z",
      "category": "Local Events"
    },
    {
      "title": "Bitter farewell to AFAD staff! Tears flooded: His wife hugged his coffin for the last time, the grieving father performed the funeral prayer.",
      "source": "Sabah",
      "url": "https://www.sabah.com.tr/yasam/afad-personeline-aci-veda-gozyaslari-sel-oldu-esi-tabutuna-son-kez-sarildi-cenaze-namazini-acili-baba-kildirdi-7603011",
      "published_date": "2026-06-14T16:51:27Z",
      "category": "Local Events"
    },
    {
      "title": "Call from Director of Communications Duran to fight disinformation: We need to say 'stop' together",
      "source": "Sabah",
      "url": "https://www.sabah.com.tr/gundem/2026/06/14/iletisim-baskani-durandan-dezenformasyonla-mucadele-cagrisi-hep-birlikte-dur-dememiz-gerekiyor",
      "published_date": "2026-06-14T16:51:27Z",
      "category": "Local Events"
    },
    {
      "title": "He ripped off the ear of the person who kidnapped his daughter!",
      "source": "Haberturk",
      "url": "https://www.haberturk.com/kizini-kaciran-kisinin-kulagini-kopardi-3891553",
      "published_date": "2026-06-14T14:40:02Z",
      "category": "Local Events"
    },
    {
      "title": "The dog ripped off the arm of the woman it attacked!",
      "source": "Haberturk",
      "url": "https://www.haberturk.com/dinlenme-tesisinde-dehset-kopek-saldirdigi-kadinin-kolunu-kopardi-3891547",
      "published_date": "2026-06-14T14:20:17Z",
      "category": "Local Events"
    },
    {
      "title": "Critical referendum in Switzerland: 10 million population limit rejected",
      "source": "Sabah",
      "url": "https://www.sabah.com.tr/dunya/isvicrede-kritik-referandum-10-milyon-nufus-siniri-reddedildi-7602941",
      "published_date": "2026-06-14T13:01:57Z",
      "category": "Local Events"
    },
    {
      "title": "Special sergeant murdered his family: 4 dead",
      "source": "Haberturk",
      "url": "https://www.haberturk.com/son-dakika-hakkari-de-aile-katliami-kayinpederinin-evini-basan-uzman-cavus-esi-dahil-4-kisiyi-oldurdu-3891543",
      "published_date": "2026-06-14T12:49:07Z",
      "category": "Local Events"
    },
    {
      "title": "Palestinian groups agreed in Cairo: Joint plan presented to mediators",
      "source": "Sabah",
      "url": "https://www.sabah.com.tr/dunya/filistinli-gruplar-kahirede-anlasti-ortak-plan-arabuluculara-sunuldu-7602933",
      "published_date": "2026-06-14T12:40:35Z",
      "category": "Local Events"
    },
    {
      "title": "Pakistan surrendered to heavy rains: 7 deaths",
      "source": "Sabah",
      "url": "https://www.sabah.com.tr/dunya/pakistan-siddetli-yagislara-teslim-oldu-7-can-kaybi-7602925",
      "published_date": "2026-06-14T12:23:14Z",
      "category": "Local Events"
    },
    {
      "title": "Condolence phone call from President Erdoğan to the family of Kirkuk Governor Agha",
      "source": "Sabah",
      "url": "https://www.sabah.com.tr/gundem/2026/06/14/cumhurbaskani-erdogandan-kerkuk-valisi-aganin-ailesine-taziye-telefonu",
      "published_date": "2026-06-14T12:22:25Z",
      "category": "Local Events"
    },
    {
      "title": "TOKİ housing campaign sales start tomorrow",
      "source": "Sabah",
      "url": "https://www.sabah.com.tr/ekonomi/toki-konut-kampanyasi-satislari-yarin-basliyor-7602923",
      "published_date": "2026-06-14T12:20:48Z",
      "category": "Local Events"
    },
    {
      "title": "Czech tourist died in accident",
      "source": "Haberturk",
      "url": "https://www.haberturk.com/son-dakika-antalyada-otomobilin-carptigi-cek-turist-hayatini-kaybetti-3891580",
      "published_date": "2026-06-14T12:18:34Z",
      "category": "Local Events"
    },
    {
      "title": "They thought they were pigs and shot their relatives!",
      "source": "Haberturk",
      "url": "https://www.haberturk.com/gelen-sesi-domuz-zannedip-akrabalarini-vurdular-1-olu-2-gozalti-3891562",
      "published_date": "2026-06-14T12:16:59Z",
      "category": "Local Events"
    },
    {
      "title": "\"It is not anyone's place to target\"",
      "source": "Haberturk",
      "url": "https://www.haberturk.com/son-dakika-celik-saygisiz-bir-dille-hedef-gostermek-kimsenin-haddi-degildir-3891576",
      "published_date": "2026-06-14T12:12:03Z",
      "category": "Local Events"
    },
    {
      "title": "Horror! He murdered his wife and beat his daughter!",
      "source": "Haberturk",
      "url": "https://www.haberturk.com/dehset-esini-katledip-kizini-darp-etti-3891575",
      "published_date": "2026-06-14T11:52:27Z",
      "category": "Local Events"
    },
    {
      "title": "Teacher disaster in Antalya",
      "source": "Haberturk",
      "url": "https://www.haberturk.com/son-dakika-antalya-da-cografya-ogretmeni-faciayi-yasatti-tayin-tartismasinda-3-cocuk-annesi-esi-ve-kayinpederini-oldurdu-3891563",
      "published_date": "2026-06-14T11:33:27Z",
      "category": "Local Events"
    },
    {
      "title": "Cabinet meets tomorrow",
      "source": "Haberturk",
      "url": "https://www.haberturk.com/kabine-toplaniyor-abd-iran-muzakereleri-nato-zirvesi-hazirliklari-masada-3891566",
      "published_date": "2026-06-14T10:43:44Z",
      "category": "Local Events"
    },
    {
      "title": "Atrocity in Antalya: Teacher husband, mother of 3 children killed his teacher wife and father-in-law",
      "source": "Sabah",
      "url": "https://www.sabah.com.tr/yasam/antalyada-vahset-ogretmen-koca-3-cocuk-annesi-ogretmen-esini-ve-kayinpederini-oldurdu-7602884",
      "published_date": "2026-06-14T10:25:48Z",
      "category": "Local Events"
    }
  ]
}