{
  "country": "turkey",
  "last_updated": "2026-06-05T13:59:40Z",
  "stories": [
    {
      "title": "US imposes sanctions on Cuban President Diaz-Canel",
      "source": "Sabah",
      "url": "https://www.sabah.com.tr/ekonomi/abdden-kuba-devlet-baskani-diaz-canele-yaptirim-karari-7597357",
      "published_date": "2026-06-05T13:34:17Z",
      "category": "Diplomacy"
    },
    {
      "title": "At the Zero Waste Forum 2026, experts evaluated the connection between zero waste and circular economy",
      "source": "Sabah",
      "url": "https://www.sabah.com.tr/gundem/2026/06/05/sifir-atik-forumu-2026da-uzmanlar-sifir-atik-ve-dongusel-ekonomi-alanindaki-baglantiyi-degerlendirdi",
      "published_date": "2026-06-05T12:44:57Z",
      "category": "Diplomacy"
    },
    {
      "title": "BREAKING NEWS | President Erdoğan announced: Ziraat, Vakıf and Halk Katılım will merge, Emlak Katılım will go public!",
      "source": "Sabah",
      "url": "https://www.sabah.com.tr/gundem/2026/06/05/son-dakika-baskan-erdogandan-onemli-aciklamalar",
      "published_date": "2026-06-05T12:35:06Z",
      "category": "Diplomacy"
    },
    {
      "title": "Mysterious death of Azerbaijani bureaucrat!",
      "source": "Haberturk",
      "url": "https://www.haberturk.com/luks-otelde-azerbaycanli-burokratin-esrarengiz-olumu-3889557",
      "published_date": "2026-06-05T10:17:46Z",
      "category": "Diplomacy"
    },
    {
      "title": "FAO: Global food prices decreased",
      "source": "Sabah",
      "url": "https://www.sabah.com.tr/ekonomi/fao-kuresel-gida-fiyatlari-geriledi-7597253",
      "published_date": "2026-06-05T10:01:17Z",
      "category": "Diplomacy"
    },
    {
      "title": "Release for 4 defendants in the harassment case in the Turkish Grand National Assembly",
      "source": "Haberturk",
      "url": "https://www.haberturk.com/son-dakika-tbmm-de-taciz-davasinda-4-adli-kontrol-karari-3889550",
      "published_date": "2026-06-05T09:09:28Z",
      "category": "Diplomacy"
    },
    {
      "title": "Minister Fidan spoke at a joint press conference with his Bangladeshi counterpart! Message of new areas of cooperation",
      "source": "Sabah",
      "url": "https://www.sabah.com.tr/gundem/2026/06/05/bakan-fidan-bangladesli-mevkidasi-ile-ortak-basin-toplantisinda-konustu-yeni-isbirligi-alanlari-mesaji",
      "published_date": "2026-06-05T08:01:48Z",
      "category": "Diplomacy"
    },
    {
      "title": "\"We continue to promote environmentally friendly business practices\"",
      "source": "Haberturk",
      "url": "https://www.haberturk.com/ticaret-bakani-omer-bolat-cevre-dostu-ticaret-uygulamalarini-tesvik-etmeyi-surduruyoruz-3889485-ekonomi",
      "published_date": "2026-06-05T07:19:37Z",
      "category": "Diplomacy"
    },
    {
      "title": "How much could the Iran War change the Middle East?",
      "source": "Haberturk",
      "url": "https://www.haberturk.com/bombalar-haritayi-cizer-cografya-gulumser-iran-savasi-ortadoguyu-ne-kadar-degistirebilir-3889479",
      "published_date": "2026-06-05T06:59:16Z",
      "category": "Diplomacy"
    },
    {
      "title": "He shot two women and ran away",
      "source": "Haberturk",
      "url": "https://www.haberturk.com/son-dakika-haberi-iki-kadina-kursun-yagdirip-kacti-denizli-haberleri-3889474",
      "published_date": "2026-06-05T06:40:16Z",
      "category": "Diplomacy"
    },
    {
      "title": "\"Hopefully it will be an unforgettable tournament!\"",
      "source": "Haberturk",
      "url": "https://www.haberturk.com/merih-demiral-insallah-unutulmaz-bir-turnuva-olacak-3889469-spor",
      "published_date": "2026-06-05T06:38:08Z",
      "category": "Diplomacy"
    },
    {
      "title": "BİM 5 June current catalog is on sale",
      "source": "Haberturk",
      "url": "https://www.haberturk.com/bim-5-haziran-2026-aktuel-katalogu-yayinda-bu-cuma-bim-marketlere-vantilator-cocuk-tableti-soundbar-geliyor-bim-2-5-haziran-aktuel-urunleri-neler-3888981",
      "published_date": "2026-06-05T05:59:44Z",
      "category": "Diplomacy"
    },
    {
      "title": "The best villages in the world have been revealed",
      "source": "Haberturk",
      "url": "https://www.haberturk.com/dunyanin-en-iyi-koyleri-belli-oldu-turkiyeden-dort-yer-listede-3889286",
      "published_date": "2026-06-05T05:59:14Z",
      "category": "Diplomacy"
    },
    {
      "title": "\"Iran and Oman will make the decision in Hormuz\"",
      "source": "Haberturk",
      "url": "https://www.haberturk.com/iran-disisleri-bakani-hurmuz-bogazinin-yonetimine-iran-ve-ummanin-karar-verecegini-yineledi-3889457",
      "published_date": "2026-06-05T05:09:51Z",
      "category": "Diplomacy"
    },
    {
      "title": "When is the Venezuela - Türkiye friendly match?",
      "source": "Haberturk",
      "url": "https://www.haberturk.com/dunya-kupasi-hazirlik-maci-venezuela-turkiye-hazirlik-maci-ne-zaman-saat-kacta-hangi-kanalda-3889350",
      "published_date": "2026-06-05T04:19:31Z",
      "category": "Diplomacy"
    },
    {
      "title": "Putin: We want to sign the peace agreement with Ukraine with the legitimate government",
      "source": "Sabah",
      "url": "https://www.sabah.com.tr/dunya/putin-ukrayna-ile-baris-anlasmasini-mesru-yonetimle-imzalamak-istiyoruz-7596974",
      "published_date": "2026-06-04T22:13:56Z",
      "category": "Diplomacy"
    },
    {
      "title": "When will the June rent increase rate be announced?",
      "source": "Haberturk",
      "url": "https://www.haberturk.com/haziran-kira-artis-orani-hesaplama-2026-haziran-ayi-kira-artis-orani-ne-zaman-aciklanacak-kira-zammi-hangi-gun-belli-olacak-3889149",
      "published_date": "2026-06-04T21:29:44Z",
      "category": "Diplomacy"
    },
    {
      "title": "When will the First Home mortgage loan applications start?",
      "source": "Haberturk",
      "url": "https://www.haberturk.com/ilk-evim-konut-kredisi-basvurulari-ne-zaman-baslayacak-dusuk-faizli-konut-kredisi-basvuru-sartlari-neler-kimlere-cikacak-3889376",
      "published_date": "2026-06-04T21:26:34Z",
      "category": "Diplomacy"
    },
    {
      "title": "Minister Fidan met with his Bangladeshi counterpart",
      "source": "Sabah",
      "url": "https://www.sabah.com.tr/gundem/2026/06/04/bakan-fidan-bangladesli-mevkidasi-ile-gorustu",
      "published_date": "2026-06-04T20:08:08Z",
      "category": "Diplomacy"
    },
    {
      "title": "IHU Board of Trustees Deputy Chairman Bilal Erdoğan: We must ensure that young people have confidence in their own heritage.",
      "source": "Sabah",
      "url": "https://www.sabah.com.tr/gundem/2026/06/04/ihu-mutevelli-heyeti-baskan-vekili-bilal-erdogan-genclerin-kendi-miraslarina-guven-duymalarini-saglamaliyiz",
      "published_date": "2026-06-04T18:42:45Z",
      "category": "Diplomacy"
    },
    {
      "title": "CHP's Tanju Özcan before the judge: Blackmail case postponed to July 13",
      "source": "Sabah",
      "url": "https://www.sabah.com.tr/gundem/2026/06/05/chpli-tanju-ozcan-hakim-karsisinda-santaj-davasi-13-temmuza-ertelendi",
      "published_date": "2026-06-05T13:44:39Z",
      "category": "Military"
    },
    {
      "title": "US soldiers raided oil tanker in Indian Ocean",
      "source": "Sabah",
      "url": "https://www.sabah.com.tr/dunya/abd-askerleri-hint-okyanusunda-petrol-tankerine-baskin-duzenledi-7597363",
      "published_date": "2026-06-05T13:43:16Z",
      "category": "Military"
    },
    {
      "title": "New developments regarding USS Gerald R. Ford have emerged! Almost turned to ashes",
      "source": "Sabah",
      "url": "https://www.sabah.com.tr/dunya/uss-gerald-r-forda-dair-yeni-gelismeler-ortaya-cikti-neredeyse-kule-donmus-7597354",
      "published_date": "2026-06-05T13:30:58Z",
      "category": "Military"
    },
    {
      "title": "Prisoner exchange between Ukraine and Russia! 185 prisoners were mutually handed over",
      "source": "Sabah",
      "url": "https://www.sabah.com.tr/dunya/ukrayna-ve-rusya-arasinda-mahkum-takasi-185-mahkum-karsilikli-teslim-edildi-7597344",
      "published_date": "2026-06-05T13:15:54Z",
      "category": "Military"
    },
    {
      "title": "Herdsmen and farmers clashed in Nigeria: 7 people died",
      "source": "Sabah",
      "url": "https://www.sabah.com.tr/dunya/nijeryada-cobanlar-ile-ciftciler-catisti-7-kisi-oldu-7597322",
      "published_date": "2026-06-05T12:52:00Z",
      "category": "Military"
    },
    {
      "title": "Record increase in electric vehicle charging during the holiday",
      "source": "Sabah",
      "url": "https://www.sabah.com.tr/ekonomi/bayramda-elektrikli-arac-sarjinda-rekor-artis-7597305",
      "published_date": "2026-06-05T12:18:05Z",
      "category": "Military"
    },
    {
      "title": "Onlayer is on the “2025 Deloitte Technology EMEA Fast 500” list",
      "source": "Haberturk",
      "url": "https://www.haberturk.com/onlayer-2025-deloitte-teknoloji-emea-fast-500-listesinde-3889598-ekonomi",
      "published_date": "2026-06-05T11:35:41Z",
      "category": "Military"
    },
    {
      "title": "Bloody ambush with a builder's outfit! \"Engin didn't come out...\" \"Don't turn up empty handed, shoot someone!\"",
      "source": "Haberturk",
      "url": "https://www.haberturk.com/son-dakika-haberi-dilan-polat-in-korumasi-can-polat-i-olduren-serhat-a-nin-ifadesi-cikti-3889449",
      "published_date": "2026-06-05T10:32:01Z",
      "category": "Military"
    },
    {
      "title": "Ukrainian Army Air Forces Command: 5 people killed and 11 injured in Russian air strikes",
      "source": "Sabah",
      "url": "https://www.sabah.com.tr/dunya/ukrayna-ordusu-hava-kuvvetleri-komutanligi-rus-hava-saldirilarinda-5-kisi-oldu-11-kisi-yaralandi-7597247",
      "published_date": "2026-06-05T09:51:43Z",
      "category": "Military"
    },
    {
      "title": "'Paid' warning from MSB",
      "source": "Haberturk",
      "url": "https://www.haberturk.com/msb-den-bedelli-uyarisi-iste-zamsiz-bedelli-askerlik-icin-son-tarih-3889529-ekonomi",
      "published_date": "2026-06-05T08:49:01Z",
      "category": "Military"
    },
    {
      "title": "Truck hit 10 vehicles! There are people injured!",
      "source": "Haberturk",
      "url": "https://www.haberturk.com/kamyon-10-araca-carpti-yaralilar-var-3889527",
      "published_date": "2026-06-05T08:15:01Z",
      "category": "Military"
    },
    {
      "title": "Terrorist operation in Pakistan: 4 militants neutralized",
      "source": "Sabah",
      "url": "https://www.sabah.com.tr/dunya/pakistanda-teror-operasyonu-4-militan-etkisiz-hale-getirildi-7597158",
      "published_date": "2026-06-05T07:45:49Z",
      "category": "Military"
    },
    {
      "title": "An unforgettable musical feast from the Russian Red Army Choir and Hayko Cepkin",
      "source": "Haberturk",
      "url": "https://www.haberturk.com/aleksandrov-rus-kizilordu-korosu-ve-hayko-cepkin-den-unutulmaz-bir-muzik-soleni-3889475",
      "published_date": "2026-06-05T06:44:08Z",
      "category": "Military"
    },
    {
      "title": "BREAKING NEWS... Minister Akın Gürlek announced! Detention decision for 104 suspects: A transaction volume of 193 billion 367 million TL was determined!",
      "source": "Sabah",
      "url": "https://www.sabah.com.tr/gundem/2026/06/05/son-dakika-bakan-akin-gurlek-acikladi-27-ilde-104-supheli-hakkinda-gozalti-karari-193-milyar-367-milyon-tllik-bir-islem-hacmi-belirlendi",
      "published_date": "2026-06-05T06:07:52Z",
      "category": "Military"
    },
    {
      "title": "The historical hoax that fooled Nazi Germany",
      "source": "Haberturk",
      "url": "https://www.haberturk.com/nazi-almanyasini-kandiran-tarihi-aldatmaca-hic-var-olmayan-bir-adam-operasyonun-seyrini-degistirdi-3888357",
      "published_date": "2026-06-05T04:42:32Z",
      "category": "Military"
    },
    {
      "title": "Who won the Survivor immunity game?",
      "source": "Haberturk",
      "url": "https://www.haberturk.com/survivor-dokunulmazlik-oyunu-kim-kazandi-4-haziran-persembe-survivor-bireysel-dokunulmazlik-oyununu-kim-aldi-3889406",
      "published_date": "2026-06-05T04:18:28Z",
      "category": "Military"
    },
    {
      "title": "1 Israeli officer killed in Hezbollah attack",
      "source": "Haberturk",
      "url": "https://www.haberturk.com/lubnan-da-hizbullah-saldirisinda-1-israil-subayi-oldu-3889443",
      "published_date": "2026-06-05T03:20:03Z",
      "category": "Military"
    },
    {
      "title": "Armed fight: Married couple lost their lives",
      "source": "Haberturk",
      "url": "https://www.haberturk.com/bursa-da-silahli-kavga-evli-cift-hayatini-kaybetti-3889439",
      "published_date": "2026-06-05T02:40:55Z",
      "category": "Military"
    },
    {
      "title": "Memorandum of understanding from Iran: There are still uncertainties that need to be clarified",
      "source": "Sabah",
      "url": "https://www.sabah.com.tr/dunya/irandan-mutabakat-aciklamasi-hala-acikliga-kavusturulmasi-gereken-belirsizlikler-var-7596973",
      "published_date": "2026-06-04T22:06:18Z",
      "category": "Military"
    },
    {
      "title": "The USA may cancel the plan to send Tomahawk missiles to Germany! The reason is Russia...",
      "source": "Sabah",
      "url": "https://www.sabah.com.tr/dunya/abd-almanyaya-tomahawk-fuzeleri-gonderme-planini-iptal-edebilir-sebebi-rusya-7596960",
      "published_date": "2026-06-04T21:33:48Z",
      "category": "Military"
    },
    {
      "title": "10-day huge sale in diesel and gasoline! Vehicle owners bought liters of fuel",
      "source": "Sabah",
      "url": "https://www.sabah.com.tr/ekonomi/motorin-ve-benzinde-10-gunluk-dev-satis-arac-sahipleri-litre-litre-akaryakit-aldi-7597303",
      "published_date": "2026-06-05T12:14:33Z",
      "category": "Energy"
    },
    {
      "title": "TAV's airports received 'Airport Carbon Accreditation'",
      "source": "Haberturk",
      "url": "https://www.haberturk.com/tav-in-tum-havalimanlari-havalimani-karbon-akreditasyonu-aldi-3889537-ekonomi",
      "published_date": "2026-06-05T08:33:04Z",
      "category": "Energy"
    },
    {
      "title": "Three awards from EMEA Finance to Rönesans Enerji",
      "source": "Haberturk",
      "url": "https://www.haberturk.com/ronesans-enerji-ye-emea-finance-ten-uc-odul-3889511-ekonomi",
      "published_date": "2026-06-05T07:48:49Z",
      "category": "Energy"
    },
    {
      "title": "Early payment plan from TMO",
      "source": "Haberturk",
      "url": "https://www.haberturk.com/ciftcileri-yakindan-ilgilendiriyor-tmo-dan-erken-odeme-plani-3889480-ekonomi",
      "published_date": "2026-06-05T07:16:53Z",
      "category": "Energy"
    },
    {
      "title": "It grows on cable, not soil!",
      "source": "Haberturk",
      "url": "https://www.haberturk.com/toprakta-degil-kabloda-yetisiyor-degeri-kirmizi-cilekten-katbekat-fazla-3889240",
      "published_date": "2026-06-05T05:59:17Z",
      "category": "Energy"
    },
    {
      "title": "Uncertainty continues in oil",
      "source": "Haberturk",
      "url": "https://www.haberturk.com/petrolde-belirsizlik-suruyor-iran-in-petrol-ihracati-son-6-yilin-en-dusugunde-3889453-ekonomi",
      "published_date": "2026-06-05T04:44:17Z",
      "category": "Energy"
    },
    {
      "title": "Young talents brought the European Championship to Türkiye in Windsurfing",
      "source": "Haberturk",
      "url": "https://www.haberturk.com/genc-yetenekler-windsorf-te-turkiye-ye-avrupa-sampiyonlugu-getirdi-3889423-spor",
      "published_date": "2026-06-04T21:10:27Z",
      "category": "Energy"
    },
    {
      "title": "The only sure way to store avocados without browning",
      "source": "Haberturk",
      "url": "https://www.haberturk.com/avokadoyu-kararmadan-saklamanin-tek-kesin-yolu-belli-oldu-3889399",
      "published_date": "2026-06-04T18:30:39Z",
      "category": "Energy"
    },
    {
      "title": "The device that draws more electricity than the oven has been revealed!",
      "source": "Haberturk",
      "url": "https://www.haberturk.com/firindan-bile-fazla-elektrik-ceken-cihaz-belli-oldu-3889318",
      "published_date": "2026-06-04T16:06:33Z",
      "category": "Energy"
    },
    {
      "title": "Simple method to peel boiled eggs easily",
      "source": "Haberturk",
      "url": "https://www.haberturk.com/yumurtayi-kabugundan-ayirmak-sandiginizdan-daha-kolay-olabilir-soguk-su-mu-karbonat-mi-yumurta-soymanin-en-etkili-yolu-belli-oldu-3889328",
      "published_date": "2026-06-04T13:23:26Z",
      "category": "Energy"
    },
    {
      "title": "Istanbul Airport's electricity comes from the sun! 240 MW solar energy move from İGA",
      "source": "Sabah",
      "url": "https://www.sabah.com.tr/ekonomi/istanbul-havalimaninin-elektrigi-gunesten-igadan-240-mwlik-gunes-enerjisi-hamlesi-7596651",
      "published_date": "2026-06-04T13:21:15Z",
      "category": "Energy"
    },
    {
      "title": "Zero Waste Festival has started",
      "source": "Haberturk",
      "url": "https://www.haberturk.com/sifir-atik-festivali-ataturk-havalimani-nda-basladi-3889298-ekonomi",
      "published_date": "2026-06-04T12:33:59Z",
      "category": "Energy"
    },
    {
      "title": "Şişecam commissioned its new solar energy investment",
      "source": "Haberturk",
      "url": "https://www.haberturk.com/sisecam-yeni-ges-yatirimini-devreye-aldi-3889307-ekonomi",
      "published_date": "2026-06-04T11:50:22Z",
      "category": "Energy"
    },
    {
      "title": "Statement from the Minister Institution for hobby gardens",
      "source": "Sabah",
      "url": "https://www.sabah.com.tr/ekonomi/bakan-kurumdan-hobi-bahceleri-icin-aciklama-7596598",
      "published_date": "2026-06-04T11:34:04Z",
      "category": "Energy"
    },
    {
      "title": "Türkiye has entered a new era in renewable energy: The target is to become a production base",
      "source": "Sabah",
      "url": "https://www.sabah.com.tr/ekonomi/turkiye-yenilenebilir-enerjide-yeni-doneme-girdi-hedef-uretim-ussu-olmak-7596580",
      "published_date": "2026-06-04T10:50:58Z",
      "category": "Energy"
    },
    {
      "title": "SOCAR Türkiye at the International 'Caspian Oil and Gas Fair'",
      "source": "Haberturk",
      "url": "https://www.haberturk.com/socar-turkiye-uluslararasi-hazar-petrol-ve-gaz-fuari-na-katildi-3889233-ekonomi",
      "published_date": "2026-06-04T07:56:46Z",
      "category": "Energy"
    },
    {
      "title": "Interference in Kentucky elections from the Zionist lobby: They spent millions to oust Massie, a politician who does not support Israel",
      "source": "Sabah",
      "url": "https://www.sabah.com.tr/dunya/israil-lobisinden-kentucky-secimlerine-mudahale-siyonist-karsiti-siyasetci-massieyi-devirmek-icin-milyonlar-harcadilar-7596000",
      "published_date": "2026-06-03T14:00:03Z",
      "category": "Energy"
    },
    {
      "title": "Increased current fuel prices",
      "source": "Haberturk",
      "url": "https://www.haberturk.com/zamli-guncel-akaryakit-fiyatlari-3-haziran-2026-benzin-ve-motorin-fiyati-ne-kadar-oldu-zamli-akaryakit-fiyat-listesi-3889013",
      "published_date": "2026-06-03T12:58:53Z",
      "category": "Energy"
    },
    {
      "title": "Pre-COP31 assessment from Climate Network",
      "source": "Haberturk",
      "url": "https://www.haberturk.com/iklim-agi-nden-cop31-oncesi-degerlendirme-3889045-ekonomi",
      "published_date": "2026-06-03T12:17:15Z",
      "category": "Energy"
    },
    {
      "title": "6 billion dollar investment for renewable energy from Türkiye! Minister Bayraktar announced his 2035 vision",
      "source": "Sabah",
      "url": "https://www.sabah.com.tr/ekonomi/yenilenebilir-enerji-icin-6-milyar-dolarlik-yatirim-bakan-bayraktar-2035-vizyonunu-acikladi-7595944",
      "published_date": "2026-06-03T12:11:37Z",
      "category": "Energy"
    },
    {
      "title": "Historical merger in participation banking",
      "source": "Haberturk",
      "url": "https://www.haberturk.com/cumhurbaskani-erdogan-dan-aciklamalar-3889619-ekonomi",
      "published_date": "2026-06-05T13:08:08Z",
      "category": "Economy"
    },
    {
      "title": "Evaluation of the banking system from Minister Bolat: There is a stable performance",
      "source": "Sabah",
      "url": "https://www.sabah.com.tr/ekonomi/bakan-bolattan-bankacilik-sistemine-yonelik-degerlendirme-istikrarli-bir-performans-var-7597336",
      "published_date": "2026-06-05T13:03:01Z",
      "category": "Economy"
    },
    {
      "title": "The net profit of the banking sector increased by 38 percent in the first 4 months and reached 363.6 billion liras.",
      "source": "Sabah",
      "url": "https://www.sabah.com.tr/ekonomi/bankacilik-sektorunun-net-kari-ilk-4-ayda-yuzde-38-artti-3636-milyar-liraya-ulasti-7597286",
      "published_date": "2026-06-05T11:27:54Z",
      "category": "Economy"
    },
    {
      "title": "Zero Waste Festival continues with all its excitement! 700 million dollars of resources for 4500 projects",
      "source": "Sabah",
      "url": "https://www.sabah.com.tr/ekonomi/bakan-kacir-2030a-isaret-etti-5-milyar-avro-sanayi-karbonsuzlastirma-yatirimi-hedefliyoruz-7597284",
      "published_date": "2026-06-05T11:25:23Z",
      "category": "Economy"
    },
    {
      "title": "\"We closely monitor price movements in the market\"",
      "source": "Haberturk",
      "url": "https://www.haberturk.com/ticaret-bakani-omer-bolat-piyasadaki-fiyat-hareketlerini-yakindan-izliyoruz-3889589-ekonomi",
      "published_date": "2026-06-05T11:10:12Z",
      "category": "Economy"
    },
    {
      "title": "Treasury will hold 3 tenders and 4 direct sales",
      "source": "Sabah",
      "url": "https://www.sabah.com.tr/ekonomi/hazine-3-ihale-ve-4-dogrudan-satis-gerceklestirecek-7597276",
      "published_date": "2026-06-05T10:59:07Z",
      "category": "Economy"
    },
    {
      "title": "$500 million global investment",
      "source": "Haberturk",
      "url": "https://www.haberturk.com/500-milyon-dolarlik-kuresel-yatirim-turkcellden-2050de-net-sifir-hedefi-3889578-teknoloji",
      "published_date": "2026-06-05T10:34:58Z",
      "category": "Economy"
    },
    {
      "title": "He killed his brother-in-law and his sister! Blood-curdling doubt!",
      "source": "Haberturk",
      "url": "https://www.haberturk.com/son-dakika-haberi-enistesi-ile-kiz-kardesini-oldurdu-kan-donduran-suphe-bursa-haberleri-3889538",
      "published_date": "2026-06-05T10:33:17Z",
      "category": "Economy"
    },
    {
      "title": "Cevdet Yılmaz: The fight against temporary shocks in inflation continues with determination",
      "source": "Sabah",
      "url": "https://www.sabah.com.tr/ekonomi/cevdet-yilmaz-enflasyonda-gecici-soklara-karsi-mucadele-kararlilikla-suruyor-7597233",
      "published_date": "2026-06-05T09:26:06Z",
      "category": "Economy"
    },
    {
      "title": "Inflation assessment from Minister Şimşek",
      "source": "Haberturk",
      "url": "https://www.haberturk.com/bakan-simsek-kalici-fiyat-istikrari-hedefimiz-dogrultusunda-politikalarimizi-surdurecegiz-3889530-ekonomi",
      "published_date": "2026-06-05T08:19:41Z",
      "category": "Economy"
    },
    {
      "title": "L'Oréal Türkiye strengthens its sustainability vision",
      "source": "Haberturk",
      "url": "https://www.haberturk.com/loral-turkiye-surdurulebilirlik-vizyonunu-guclendiriyor-3889524-ekonomi",
      "published_date": "2026-06-05T08:17:53Z",
      "category": "Economy"
    },
    {
      "title": "5-month inflation difference in salary increases has been revealed",
      "source": "Haberturk",
      "url": "https://www.haberturk.com/son-dakika-maas-zamlarinda-5-aylik-enflasyon-farki-belli-oldu-3889491-ekonomi",
      "published_date": "2026-06-05T08:04:55Z",
      "category": "Economy"
    },
    {
      "title": "“We are working for a Türkiye that grows in harmony with nature”",
      "source": "Haberturk",
      "url": "https://www.haberturk.com/enerji-ve-tabii-kaynaklar-bakani-alparslan-bayraktar-dogayla-uyumlu-buyuyen-bir-turkiye-icin-calisiyoruz-3889508-ekonomi",
      "published_date": "2026-06-05T07:39:18Z",
      "category": "Economy"
    },
    {
      "title": "May inflation announced",
      "source": "Haberturk",
      "url": "https://www.haberturk.com/son-dakika-mayis-ayi-enflasyonu-aciklandi-3889481-ekonomi",
      "published_date": "2026-06-05T07:25:31Z",
      "category": "Economy"
    },
    {
      "title": "June rent increase ceiling has been announced",
      "source": "Haberturk",
      "url": "https://www.haberturk.com/son-dakika-haziran-ayi-kira-zam-tavani-belli-oldu-3889484-ekonomi",
      "published_date": "2026-06-05T07:22:03Z",
      "category": "Economy"
    },
    {
      "title": "How much will the civil servant's raise be?",
      "source": "Haberturk",
      "url": "https://www.haberturk.com/memur-maas-zammi-hesaplama-2026-5-aylik-enflasyon-farki-ile-en-dusuk-memur-emekli-maasi-ne-kadar-olacak-3889049",
      "published_date": "2026-06-05T07:16:17Z",
      "category": "Economy"
    },
    {
      "title": "Retirement raise calculation",
      "source": "Haberturk",
      "url": "https://www.haberturk.com/emekli-zammi-hesaplama-son-dakika-5-aylik-enflasyon-aciklandi-temmuz-2026-en-dusuk-emekli-maasi-ne-kadar-olacak-3889488",
      "published_date": "2026-06-05T07:07:14Z",
      "category": "Economy"
    },
    {
      "title": "TÜİK announced May inflation!",
      "source": "Haberturk",
      "url": "https://www.haberturk.com/tuik-mayis-ayi-enflasyon-orani-acikladi-2026-mayis-enflasyon-rakamlari-ne-kadar-dustu-mu-yukseldi-mi-5-aylik-enflasyon-farki-ne-kadar-oldu-3889466",
      "published_date": "2026-06-05T07:07:13Z",
      "category": "Economy"
    },
    {
      "title": "June rent increase rate has been announced!",
      "source": "Haberturk",
      "url": "https://www.haberturk.com/haziran-2026-kira-artis-orani-belli-oldu-tefe-tufe-haziran-kira-zam-orani-ne-kadar-oldu-bu-ayki-kira-zammi-nasil-hesaplanir-haziran-kira-artis-orani-hesaplama-3889472",
      "published_date": "2026-06-05T07:06:07Z",
      "category": "Economy"
    },
    {
      "title": "How much will the July retirement raise be?",
      "source": "Haberturk",
      "url": "https://www.haberturk.com/emekli-zammi-son-dakika-temmuz-2026-5-aylik-enflasyon-farki-ile-ssk-bag-kur-en-dusuk-emekli-maasi-ne-kadar-olacak-3889263",
      "published_date": "2026-06-05T07:05:57Z",
      "category": "Economy"
    },
    {
      "title": "The decision on the Reyhanlı attack has been announced!",
      "source": "Haberturk",
      "url": "https://www.haberturk.com/son-dakika-reyhanli-saldirisinda-karar-aciklandi-3889637",
      "published_date": "2026-06-05T13:31:17Z",
      "category": "Local Events"
    },
    {
      "title": "BREAKING NEWS... Fight with stones, sticks and knives between relatives of Narin Güran and Nevzat Bahtiyar! His son and nephew were injured...",
      "source": "Sabah",
      "url": "https://www.sabah.com.tr/yasam/sosyal-medyada-narin-cinayeti-tartismasi-sopali-bicakli-kavgaya-dondu-nevzat-bahtiyar-ile-narin-akrabalari-kavga-etti-7597329",
      "published_date": "2026-06-05T13:11:04Z",
      "category": "Local Events"
    },
    {
      "title": "Last Minute | The verdict was announced in the bomb attack case in Reyhanlı, Hatay: 3 thousand 921 years of imprisonment with 53 aggravated life sentences.",
      "source": "Sabah",
      "url": "https://www.sabah.com.tr/gundem/2026/06/05/son-dakika-hatay-reyhanlidaki-bombali-saldiri-davasinda-karar-aciklandi-53-kez-agirlastirilmis-muebbet-ile-3-bin-921-yil-hapis-cezasi",
      "published_date": "2026-06-05T13:07:29Z",
      "category": "Local Events"
    },
    {
      "title": "BREAKING NEWS | The blasphemy scandal continues in CHP: The microphone left open during the live broadcast gave it away!",
      "source": "Sabah",
      "url": "https://www.sabah.com.tr/yasam/son-dakika-chpde-kufur-skandali-bitmiyor-canli-yayinda-acik-kalan-mikrofon-ele-verdi-7597307",
      "published_date": "2026-06-05T12:46:45Z",
      "category": "Local Events"
    },
    {
      "title": "Group meeting question to Kılıçdaroğlu",
      "source": "Haberturk",
      "url": "https://www.haberturk.com/son-dakika-kilicdaroglu-na-grup-toplantisi-sorusu-3889507",
      "published_date": "2026-06-05T12:29:49Z",
      "category": "Local Events"
    },
    {
      "title": "The murder that shocked the USA! Hollywood star was stabbed to death",
      "source": "Sabah",
      "url": "https://www.sabah.com.tr/dunya/dunyayi-soke-eden-cinayet-hollywood-yildizi-bicaklanarak-katledildi-7597308",
      "published_date": "2026-06-05T12:24:52Z",
      "category": "Local Events"
    },
    {
      "title": "Memorial published its Sustainability Report",
      "source": "Haberturk",
      "url": "https://www.haberturk.com/memorial-saglik-grubu-2025-surdurulebilirlik-raporunu-yayimladi-3889604-ekonomi",
      "published_date": "2026-06-05T12:13:55Z",
      "category": "Local Events"
    },
    {
      "title": "Artificial intelligence investigation into Meta",
      "source": "Haberturk",
      "url": "https://www.haberturk.com/rekabet-kurumundan-metaya-yapay-zeka-sorusturmasi-3889606-teknoloji",
      "published_date": "2026-06-05T12:11:09Z",
      "category": "Local Events"
    },
    {
      "title": "\"Artificial Intelligence in the Türkiye Century\"",
      "source": "Haberturk",
      "url": "https://www.haberturk.com/cumhurbaskani-yardimcisi-yilmaz-ai-tomorrow-summit-2026-etkinliginde-konustu-3889599-teknoloji",
      "published_date": "2026-06-05T11:37:50Z",
      "category": "Local Events"
    },
    {
      "title": "Competition Board investigates Meta: WhatsApp opens the way for different artificial intelligence assistants",
      "source": "Sabah",
      "url": "https://www.sabah.com.tr/ekonomi/rekabet-kurulundan-metaya-sorusturma-whatsappta-farkli-yapay-zeka-asistanlarinin-onu-aciliyor-7597275",
      "published_date": "2026-06-05T10:50:37Z",
      "category": "Local Events"
    },
    {
      "title": "Zehra was a university student... Heartbreaking ending in the student dormitory!",
      "source": "Haberturk",
      "url": "https://www.haberturk.com/son-dakika-haberi-zehra-kacar-universite-ogrencisiydi-ogrenci-yurdunda-yurek-yakan-son-3889459",
      "published_date": "2026-06-05T10:32:42Z",
      "category": "Local Events"
    },
    {
      "title": "Minister Çiftçi: The number of citizens who downloaded the HAYAT 112 Emergency application reached 552 thousand 150",
      "source": "Sabah",
      "url": "https://www.sabah.com.tr/gundem/2026/06/05/bakan-ciftci-hayat-112-acil-uygulamasini-indiren-vatandas-sayisi-552-bin-150ye-ulasti",
      "published_date": "2026-06-05T10:30:13Z",
      "category": "Local Events"
    },
    {
      "title": "BREAKING NEWS... Corruption operation against Manavgat Municipality: 3 suspects in custody",
      "source": "Sabah",
      "url": "https://www.sabah.com.tr/gundem/2026/06/05/son-dakika-manavgat-belediyesine-yolsuzluk-operasyonu-3-supheli-gozaltinda",
      "published_date": "2026-06-05T10:28:14Z",
      "category": "Local Events"
    },
    {
      "title": "CHP's Kilis Mayor Hakan Bilecen resigned from his party! He criticized his private management",
      "source": "Sabah",
      "url": "https://www.sabah.com.tr/yasam/chpli-kilis-belediye-baskani-hakan-bilecen-partisinden-istifa-etti-7597259",
      "published_date": "2026-06-05T10:23:09Z",
      "category": "Local Events"
    },
    {
      "title": "Plane evacuated due to power bank",
      "source": "Haberturk",
      "url": "https://www.haberturk.com/powerbank-nedeniyle-ucaktaki-yolcular-tahliye-edildi-3889510",
      "published_date": "2026-06-05T10:05:37Z",
      "category": "Local Events"
    },
    {
      "title": "The car the judge was driving fell from 2 meters",
      "source": "Haberturk",
      "url": "https://www.haberturk.com/hakimin-kullandigi-arac-2-metreden-dustu-3889554",
      "published_date": "2026-06-05T10:04:58Z",
      "category": "Local Events"
    },
    {
      "title": "BREAKING NEWS | Can Polat murder file sent to Istanbul",
      "source": "Sabah",
      "url": "https://www.sabah.com.tr/gundem/2026/06/05/son-dakika-can-polat-cinayeti-dosyasi-istanbula-gonderildi",
      "published_date": "2026-06-05T09:38:47Z",
      "category": "Local Events"
    },
    {
      "title": "They died for the sake of beauty! 2 women, same doctor: This time Melike is the victim!",
      "source": "Sabah",
      "url": "https://www.sabah.com.tr/yasam/kalca-dolgusu-yaptirmak-icin-gitmisti-melike-guzellik-ugruna-canindan-oldu-ayni-doktor-yine-olum-sacti-7597229",
      "published_date": "2026-06-05T09:17:39Z",
      "category": "Local Events"
    },
    {
      "title": "He was missing, found dead in the irrigation pond!",
      "source": "Haberturk",
      "url": "https://www.haberturk.com/sulama-havuzunda-facia-kayip-cocuk-olu-bulundu-3889549",
      "published_date": "2026-06-05T09:01:04Z",
      "category": "Local Events"
    },
    {
      "title": "High-speed train is one step closer to Samsun",
      "source": "Haberturk",
      "url": "https://www.haberturk.com/hizli-tren-samsun-a-bir-adim-daha-yaklasti-3889547-ekonomi",
      "published_date": "2026-06-05T08:59:24Z",
      "category": "Local Events"
    }
  ]
}